<?xml version="1.0" encoding="utf-8"?>
<!DOCTYPE Map>
<Map srs="+proj=merc +a=6378137 +b=6378137 +lat_ts=0.0 +lon_0=0.0 +x_0=0.0 +y_0=0.0 +k=1.0 +units=m +nadgrids=@null +wktext +no_defs +over">
    <Parameters>
        <Parameter name="sizes">512, 512</Parameter>
    </Parameters>

    <Layer name="layer" srs="+proj=latlong +datum=WGS84">
        <StyleName>lines</StyleName>
        <Datasource>
            <Parameter name="type">csv</Parameter>
            <Parameter name="inline">
                wkt
                "POLYGON ((17.4639182 49.9903224,17.4639881 49.9903758,17.4640339 49.9903553,17.4640868 49.9903969,17.4640706 49.9904054,17.4640889 49.9904202,17.4641048 49.9904132,17.4641332 49.9904396,17.4641179 49.9904463,17.4641354 49.9904607,17.4641487 49.9904539,17.4641785 49.990478,17.4641627 49.990486,17.4641801 49.9905007,17.4641963 49.9904926,17.4642216 49.9905147,17.4642046 49.9905227,17.4642256 49.9905403,17.4642552 49.9905281,17.4643893 49.9906373,17.4643686 49.9906477,17.4643892 49.9906647,17.4644091 49.9906562,17.4644158 49.9906621,17.4644126 49.9906636,17.4644467 49.9906917,17.4644625 49.9907013,17.4644525 49.9907079,17.4644674 49.9907225,17.4644819 49.9907167,17.4645232 49.990759,17.4644832 49.9907752,17.4645338 49.9908347,17.4646013 49.9908114,17.4645881 49.9907921,17.4646237 49.9907819,17.4646271 49.9907864,17.4647267 49.9907553,17.4647239 49.990751,17.464767 49.990739,17.4647707 49.9907433,17.4648006 49.9907354,17.4647965 49.9907288,17.464843 49.9907167,17.4648584 49.9907359,17.4648811 49.9907281,17.4648669 49.9907089,17.4649127 49.9906941,17.464914 49.9906957,17.464934 49.9906896,17.4649329 49.990688,17.4649779 49.990676,17.4649922 49.9906962,17.4650176 49.990689,17.4650029 49.9906687,17.4650395 49.9906568,17.4650409 49.9906586,17.465059 49.9906534,17.4650577 49.9906513,17.4650903 49.990642,17.4651062 49.9906611,17.4651265 49.9906537,17.4651136 49.9906335,17.4651454 49.9906238,17.4651468 49.9906257,17.4651656 49.9906201,17.4651637 49.9906175,17.4651988 49.9906069,17.4652099 49.9906281,17.4652344 49.9906208,17.4652183 49.9906009,17.4652521 49.9905898,17.4652535 49.9905916,17.4652704 49.9905871,17.4652683 49.9905845,17.4652792 49.9905809,17.4652965 49.9906029,17.4653673 49.9905823,17.4653424 49.9905473,17.4654084 49.9905272,17.4653804 49.9905112,17.4653827 49.9905092,17.465366 49.9905013,17.4653636 49.990503,17.4653262 49.9904836,17.4653282 49.9904818,17.4653109 49.9904724,17.4653086 49.9904752,17.4652712 49.9904557,17.465273 49.9904539,17.4652565 49.9904454,17.4652537 49.9904473,17.4652165 49.990428,17.4652188 49.9904262,17.465202 49.9904177,17.4651996 49.9904195,17.4651616 49.9904002,17.4651629 49.9903989,17.4651466 49.9903914,17.4651455 49.9903925,17.4651062 49.9903735,17.4651074 49.9903721,17.4650906 49.9903643,17.465089 49.9903657,17.4650505 49.9903465,17.4650529 49.9903446,17.4650435 49.9903404,17.4650414 49.9903422,17.46499 49.9903166,17.4649917 49.9903145,17.4649706 49.9903088,17.4649699 49.9903109,17.4649224 49.9903029,17.4649244 49.9903007,17.4649022 49.9902968,17.4649013 49.9902989,17.4648676 49.9902931,17.4648689 49.9902908,17.4648478 49.9902866,17.4648467 49.9902888,17.4648139 49.9902823,17.4648194 49.9902746,17.4647976 49.9902675,17.464722 49.9902584,17.4646986 49.9902609,17.464702 49.9902685,17.4646668 49.9902673,17.464667 49.9902649,17.4646434 49.9902634,17.4646442 49.9902657,17.4646104 49.9902621,17.4646109 49.9902597,17.4645873 49.9902582,17.4645855 49.9902597,17.4645504 49.9902569,17.4645509 49.9902543,17.4645297 49.9902527,17.4645313 49.9902555,17.4644942 49.990257,17.4644941 49.9902549,17.4644723 49.9902545,17.4644717 49.9902565,17.46442 49.9902584,17.4644199 49.9902563,17.4643969 49.9902561,17.4643972 49.990258,17.4642842 49.9902605,17.4641612 49.990273,17.4640263 49.9903103,17.4639674 49.9902929,17.4639182 49.9903224),(17.4642521 49.9903579,17.4643597 49.9903482,17.4645129 49.9903487,17.4646094 49.9903547,17.4645885 49.9904416,17.4646464 49.9904454,17.464646 49.9904473,17.4646824 49.9904517,17.4646828 49.99045,17.4647477 49.9904562,17.4647471 49.9904583,17.4647834 49.9904616,17.4647839 49.9904598,17.4648408 49.9904655,17.4648551 49.990407,17.4648587 49.9904074,17.46486 49.9904015,17.464853 49.9904008,17.4648582 49.9903781,17.4649053 49.9903884,17.4649605 49.9904053,17.46504 49.9904389,17.4651793 49.9905044,17.4651877 49.9905155,17.465183 49.9905217,17.4651668 49.9905217,17.4647201 49.9906575,17.4646533 49.9906968,17.464514 49.9905764,17.4645634 49.9905539,17.4645201 49.9905167,17.4644696 49.9905388,17.4642521 49.9903579))"
            </Parameter>
        </Datasource>
    </Layer>

    <Style name="lines">
        <Rule>
            <LineSymbolizer
                stroke="red"
                stroke-width="1"
                />

            <MarkersSymbolizer
                placement="interior"
                ignore-placement="true"
                allow-overlap="true"
                fill="blue"
                width="15"
                height="15"
                />
            <MarkersSymbolizer
                placement="point"
                ignore-placement="true"
                allow-overlap="true"
                fill="green"
                width="15"
                height="15"
                />
            <MarkersSymbolizer
                placement="polylabel"
                ignore-placement="true"
                allow-overlap="true"
                fill="red"
                width="15"
                height="15"
                />

            <TextSymbolizer
                placement="interior"
                placement-type="simple"
                placements="C,N,S,W,E,NE,SE,NW,SW"
                face-name="DejaVu Sans Book"
                size="12"
                fill="blue"
                halo-radius="1"
                halo-fill="white"
                dx="12"
                dy="12"
                >
                "Interior"
            </TextSymbolizer>
            <TextSymbolizer
                placement="centroid"
                placement-type="simple"
                placements="C,N,S,W,E,NE,SE,NW,SW"
                face-name="DejaVu Sans Book"
                size="12"
                fill="green"
                halo-radius="1"
                halo-fill="white"
                dx="12"
                dy="12"
                >
                "Centroid"
            </TextSymbolizer>
            <TextSymbolizer
                placement="polylabel"
                placement-type="simple"
                placements="C,N,S,W,E,NE,SE,NW,SW"
                face-name="DejaVu Sans Book"
                size="12"
                fill="red"
                halo-radius="1"
                halo-fill="white"
                dx="12"
                dy="12"
                >
                "Polylabel"
            </TextSymbolizer>
        </Rule>
    </Style>
</Map>
