<?xml version="1.0" encoding="utf-8"?>
<!DOCTYPE Map>
<Map srs="+proj=merc +a=6378137 +b=6378137 +lat_ts=0.0 +lon_0=0.0 +x_0=0.0 +y_0=0.0 +k=1.0 +units=m +nadgrids=@null +wktext +no_defs +over">
    <Parameters>
        <Parameter name="sizes">512, 512</Parameter>
    </Parameters>

    <Layer name="layer" srs="+proj=latlong +datum=WGS84">
        <StyleName>lines</StyleName>
        <Datasource>
            <Parameter name="type">csv</Parameter>
            <Parameter name="inline">
                wkt
                "POLYGON ((17.2087629 50.2326303,17.2087724 50.2328782,17.210163 50.2328736,17.2131333 50.2337427,17.214975 50.2333,17.215415 50.234024,17.215895 50.233869,17.217971 50.233357,17.218752 50.234481,17.217953 50.234796,17.216759 50.235204,17.2161109 50.2355652,17.2155951 50.2359611,17.2150661 50.2353149,17.2150202 50.2353339,17.215229 50.2357225,17.2153451 50.2359968,17.215415 50.2360772,17.2151472 50.236327,17.2146933 50.2366557,17.2135203 50.2367877,17.2140253 50.2371317,17.2128873 50.2377027,17.2120683 50.2379267,17.2123783 50.2379547,17.2128857 50.237739,17.214075 50.237214,17.215048 50.236428,17.2158736 50.2359088,17.2162467 50.2356408,17.2166661 50.2353897,17.216952 50.235237,17.218058 50.236029,17.217113 50.23668,17.22126 50.235137,17.221522 50.2354,17.221275 50.235402,17.221619 50.235687,17.222066 50.235496,17.222404 50.235824,17.220743 50.236519,17.222624 50.237332,17.21965 50.238924,17.2201 50.239125,17.21741 50.240863,17.216954 50.241721,17.217513 50.242079,17.2182 50.241931,17.2182 50.241659,17.222743 50.239225,17.223107 50.239798,17.22319 50.240624,17.22294 50.240769,17.2216625 50.2415504,17.2186163 50.2431321,17.2188074 50.2431387,17.2214147 50.2419334,17.223427 50.2408418,17.223699 50.241339,17.2219465 50.2422174,17.2202126 50.2429148,17.219914 50.243381,17.2194601 50.2436866,17.2194893 50.2437659,17.219969 50.2435481,17.221272 50.242839,17.222346 50.244034,17.221647 50.244351,17.220948 50.244668,17.222075 50.244684,17.222625 50.244216,17.224575 50.244993,17.224681 50.245098,17.2249 50.245331,17.224379 50.245704,17.22505 50.24559,17.225494 50.246075,17.225397 50.24635,17.224525 50.246348,17.223504 50.246853,17.223359 50.246985,17.222232 50.246905,17.221699 50.247474,17.2212 50.247952,17.222325 50.24836,17.221847 50.248486,17.22154 50.248999,17.2221576 50.2490951,17.2222658 50.2489739,17.2223427 50.2488772,17.2224787 50.2487534,17.2226609 50.2486414,17.2228561 50.2485346,17.2231723 50.2484002,17.223358 50.2483105,17.2237157 50.248086,17.2240999 50.2479118,17.2243499 50.2478338,17.2244958 50.2478015,17.2247451 50.247766,17.2249292 50.2476965,17.2250854 50.2476113,17.2252769 50.247454,17.2254968 50.2473505,17.2256386 50.2471845,17.2257049 50.2469839,17.2257515 50.2469116,17.2258328 50.2468242,17.2260797 50.2466951,17.2262955 50.2467658,17.2264141 50.2468185,17.2265833 50.2468176,17.2268644 50.2469305,17.2270932 50.2469451,17.227231 50.2469467,17.2274816 50.2468751,17.2275699 50.2469265,17.2276904 50.2469342,17.2277679 50.2469657,17.2278243 50.2470002,17.2278759 50.2471537,17.2278834 50.2472823,17.2278399 50.2473856,17.2278011 50.247414,17.2276257 50.2474823,17.2274972 50.247558,17.2270674 50.2478486,17.2269321 50.2479239,17.2268491 50.2480425,17.2267042 50.2481522,17.2265594 50.2482888,17.2262872 50.248449,17.2259139 50.2487108,17.2255651 50.2489242,17.2253175 50.2490319,17.2252801 50.2490957,17.2252869 50.2491403,17.2253216 50.2491823,17.2254061 50.2491941,17.2256516 50.249002,17.2264774 50.2485571,17.2271975 50.2480675,17.2276288 50.2477942,17.2276782 50.2478819,17.227736 50.2479519,17.2278468 50.2481224,17.2281625 50.2485208,17.2282121 50.248599,17.2281815 50.2486634,17.2281291 50.2487351,17.2280163 50.2488427,17.2279306 50.2489521,17.2278075 50.249037,17.2276674 50.249122,17.227561 50.2492263,17.2275038 50.249322,17.2275098 50.2494371,17.2276108 50.249449,17.2276483 50.2493979,17.2280306 50.2490513,17.2282184 50.2488402,17.2284648 50.2488505,17.2285286 50.2489296,17.2286215 50.2490204,17.2288961 50.2491906,17.2292388 50.2493715,17.2293129 50.2494249,17.2293285 50.249501,17.2292877 50.2495867,17.2291646 50.2497158,17.2288763 50.2499359,17.2284851 50.2501989,17.2280893 50.2504475,17.2277398 50.2507078,17.2275235 50.2508619,17.2273331 50.250938,17.2272413 50.2509542,17.2271774 50.251012,17.2271134 50.2511139,17.2270665 50.2511507,17.2270148 50.2511739,17.2269516 50.2511831,17.2269455 50.2512801,17.2269823 50.251315,17.2270451 50.25131,17.2271613 50.2511972,17.2273021 50.2510436,17.2275466 50.2509211,17.2277776 50.250818,17.2280815 50.2507182,17.2282803 50.2505524,17.2287415 50.2501872,17.2292258 50.2498179,17.2295722 50.2495835,17.2297905 50.2495155,17.2299842 50.2495078,17.2303274 50.2496201,17.2304348 50.2496902,17.2304855 50.249754,17.23038 50.2498757,17.2303026 50.2499759,17.2300578 50.2501811,17.229949 50.2502625,17.2297416 50.2504038,17.2295682 50.2505474,17.2293553 50.2507679,17.229137 50.2508909,17.2289214 50.2510405,17.2288058 50.2510773,17.2287025 50.2511679,17.2286589 50.2512269,17.2285896 50.2512755,17.2284876 50.2513132,17.228444 50.2513722,17.228389 50.2514173,17.2283216 50.2514527,17.2282924 50.2515083,17.2282951 50.251535,17.2283277 50.2515459,17.2283699 50.2515398,17.2284603 50.2514881,17.2286827 50.2513389,17.2288738 50.2512583,17.2289643 50.2512067,17.2290275 50.2511091,17.2292594 50.2509429,17.2293668 50.2509144,17.2294769 50.2508033,17.2298901 50.2505018,17.2300489 50.2503705,17.2301152 50.2502687,17.230441 50.2500402,17.2305787 50.2499979,17.2306406 50.2500249,17.2310023 50.2501447,17.2311171 50.2501042,17.2313036 50.2500827,17.2314505 50.2500184,17.2315905 50.2499968,17.2317211 50.2499976,17.2317835 50.2500168,17.2317782 50.2500508,17.2317141 50.250081,17.2312223 50.2504513,17.2312124 50.2504714,17.2310145 50.2506399,17.2309058 50.2507475,17.2307976 50.2508424,17.2308241 50.2509012,17.2308692 50.2509104,17.2309719 50.2508294,17.2310733 50.2507121,17.231373 50.2505425,17.2317476 50.2502358,17.2322601 50.2498846,17.232433 50.2497421,17.2325942 50.2496657,17.2327284 50.2495821,17.2329585 50.2496158,17.2332466 50.2495655,17.2334005 50.2495817,17.2335777 50.2496111,17.2337522 50.2496575,17.2333085 50.2498779,17.2331803 50.2500156,17.2330099 50.2501096,17.232869 50.2501638,17.2329456 50.2502148,17.2328731 50.2502644,17.2328274 50.2503421,17.2327411 50.2504116,17.2326073 50.2505473,17.2324016 50.2507219,17.2320943 50.2509541,17.2318059 50.25113,17.2317651 50.2511937,17.2317022 50.251267,17.2315562 50.2513977,17.2312128 50.2516628,17.2310258 50.2517516,17.2309136 50.2518425,17.2302556 50.2523275,17.2299907 50.2524993,17.2298118 50.2526352,17.229866 50.2526694,17.2301429 50.2524715,17.2306336 50.252171,17.2310375 50.2518662,17.2314636 50.2515546,17.2317392 50.2513764,17.232151 50.2510394,17.2329776 50.2503894,17.2334307 50.250085,17.233778 50.2498633,17.2340093 50.2497073,17.234183 50.2498865,17.2342494 50.2502747,17.2342771 50.2503248,17.2341269 50.250452,17.2339679 50.2505919,17.2337912 50.2507131,17.2336825 50.2507944,17.2335521 50.2509273,17.2333639 50.2510786,17.233285 50.2511883,17.2328575 50.2515106,17.2325836 50.251683,17.2324743 50.2517245,17.2323812 50.2517936,17.2322677 50.2519195,17.2321809 50.25197,17.2321005 50.2520538,17.2319782 50.2521784,17.2317635 50.2523677,17.2314298 50.2526156,17.2310282 50.2529033,17.2307537 50.25308,17.2306701 50.2531321,17.2306565 50.2531753,17.2306878 50.253195,17.2307734 50.2531565,17.2311727 50.2528902,17.2315708 50.252623,17.231894 50.2524377,17.2323222 50.2520856,17.2325972 50.2518163,17.2327019 50.251717,17.2328112 50.2516408,17.2331009 50.2514633,17.2334819 50.2512058,17.2338163 50.250967,17.2341387 50.2506877,17.2344064 50.2503615,17.2345863 50.2503221,17.2348791 50.2503364,17.2352868 50.2503624,17.2353765 50.2504035,17.2353711 50.2504384,17.2353357 50.2504892,17.2351353 50.2506308,17.2349865 50.2507493,17.2348738 50.250932,17.2348397 50.2509872,17.2345713 50.2513011,17.2342598 50.2515835,17.2342204 50.2516004,17.2339809 50.2517029,17.2339335 50.2517993,17.2339155 50.2518875,17.2339066 50.2519448,17.2339015 50.2520592,17.2338762 50.2522943,17.2338049 50.252427,17.2338079 50.2525037,17.2337841 50.2526125,17.2337719 50.2526912,17.2337454 50.2527293,17.2337318 50.2527725,17.2338281 50.2529919,17.2338451 50.2531034,17.2338525 50.2531877,17.2338408 50.2532261,17.2335573 50.2535115,17.2336165 50.2535569,17.2341774 50.2531599,17.2343084 50.2529876,17.2343931 50.2528762,17.2348226 50.2523882,17.2350613 50.2521487,17.2353318 50.2519672,17.2355008 50.25187,17.2356413 50.2517892,17.2358724 50.2516531,17.2361512 50.2515182,17.2363785 50.2514935,17.2365022 50.2514925,17.2366347 50.2515231,17.2366671 50.251562,17.2366914 50.2515961,17.2366716 50.2516508,17.2364811 50.2518487,17.2362264 50.2520497,17.2360873 50.2521465,17.2360596 50.2522071,17.2359837 50.2522672,17.2358563 50.2524246,17.2357523 50.2524801,17.235696 50.2524408,17.2356532 50.2524513,17.2355988 50.252492,17.2355791 50.2525304,17.2355615 50.2525998,17.2355375 50.2526742,17.2355253 50.2527619,17.2353955 50.2529171,17.2352843 50.2530144,17.2352213 50.2531039,17.2351384 50.2532024,17.2350706 50.2532758,17.2349493 50.2534668,17.2348743 50.2535415,17.2348367 50.2537017,17.2349855 50.2535875,17.2351545 50.2533706,17.235479 50.2530056,17.2358232 50.2525587,17.236157 50.2522871,17.2363624 50.252081,17.2365029 50.2520384,17.2366122 50.2519695,17.2367507 50.2518402,17.2367529 50.2517988,17.2368426 50.2517614,17.236931 50.2517229,17.2369996 50.2517229,17.237039 50.2517343,17.2370845 50.2517504,17.2371627 50.2518216,17.2371599 50.2518832,17.2371097 50.2519418,17.2369698 50.252071,17.2369846 50.2521722,17.2370499 50.252194,17.2371552 50.2522228,17.2372218 50.2522801,17.237251 50.2523128,17.2372558 50.2523705,17.2372259 50.2524304,17.237179 50.2524671,17.2370852 50.2524965,17.2369942 50.2525083,17.2368301 50.2524623,17.2366489 50.2524588,17.2365319 50.2523953,17.2363891 50.2524169,17.2361956 50.2524651,17.2360612 50.2525866,17.2361156 50.2527302,17.2361158 50.2529153,17.2360706 50.2530154,17.2359517 50.2531821,17.23582 50.2533073,17.2357579 50.2534227,17.235748 50.2535775,17.2357415 50.253746,17.2357365 50.2538504,17.2357242 50.2540023,17.2357421 50.2540776,17.2357626 50.2541538,17.2358314 50.2542007,17.2358666 50.2542825,17.2358529 50.2543267,17.2358214 50.2544286,17.2356413 50.2545789,17.2355397 50.2546636,17.2352415 50.2548957,17.2350154 50.2550086,17.2347481 50.2550963,17.2345782 50.255174,17.2345222 50.2553438,17.2350157 50.2553363,17.2352122 50.255247,17.2355596 50.2551337,17.2359271 50.2549539,17.2363332 50.2546646,17.2363739 50.2546356,17.2366968 50.2544168,17.2369474 50.2542006,17.2371013 50.2540714,17.2372405 50.2539194,17.2373706 50.2537805,17.2375517 50.2536484,17.2377158 50.253499,17.2380296 50.2532571,17.238231 50.2530728,17.2383171 50.2529394,17.2384382 50.2527674,17.2384695 50.2526422,17.2385803 50.2525515,17.2386835 50.2525014,17.2387197 50.25247,17.2387604 50.2524347,17.2388303 50.252357,17.2389019 50.2522857,17.2390068 50.2521867,17.2390863 50.2520969,17.2391893 50.251996,17.2390411 50.2524599,17.2389779 50.2526221,17.2389802 50.2526981,17.239071 50.2526759,17.2393193 50.2518536,17.2393607 50.2517194,17.2393953 50.2516698,17.2394049 50.251656,17.2394728 50.2516604,17.2395971 50.2516992,17.2398022 50.2518004,17.2401006 50.2519476,17.2401692 50.2519917,17.240195 50.2520463,17.2401119 50.2522789,17.2401373 50.2523781,17.2402171 50.2524997,17.2402304 50.2526406,17.2401445 50.2527359,17.2400193 50.2528747,17.2399036 50.2529486,17.2398131 50.2529961,17.2398483 50.2530959,17.239879 50.2531336,17.239968 50.2532425,17.2402638 50.2533691,17.2404378 50.2535274,17.2404627 50.2536573,17.2404219 50.2537654,17.2403291 50.253922,17.2402821 50.2540126,17.240259 50.2540624,17.2402511 50.2541424,17.2402482 50.2541713,17.24022 50.2542309,17.240218 50.2542352,17.2402797 50.2542681,17.2403789 50.254306,17.2405424 50.2543417,17.2406577 50.2543708,17.2407626 50.2544118,17.2408346 50.2544833,17.2408612 50.2545663,17.2407986 50.2546969,17.2407168 50.2548499,17.2405928 50.2550514,17.2404954 50.2551978,17.2404215 50.2553196,17.2404267 50.2553859,17.2404996 50.2554233,17.2420812 50.2562007,17.2425466 50.2564989,17.2425954 50.256519,17.2427171 50.2565972,17.2428008 50.2566658,17.2428718 50.2567354,17.243654 50.257307,17.2443511 50.257426,17.2443133 50.2575248,17.244205 50.2576136,17.2440157 50.2578256,17.2437883 50.2580649,17.2436543 50.2582199,17.2433044 50.2585317,17.2430805 50.2586928,17.2423593 50.2593541,17.2422763 50.2594897,17.2428157 50.2594602,17.243146 50.2594422,17.243202 50.2593816,17.2443616 50.2584114,17.2445964 50.2582059,17.2447197 50.2581289,17.2449258 50.2581267,17.2450758 50.2581498,17.2452147 50.2581803,17.245394 50.2583146,17.2454808 50.2584704,17.2455282 50.2586303,17.2451863 50.2591526,17.2452604 50.2592446,17.2458324 50.2592668,17.246223 50.2593468,17.2462922 50.2595635,17.2462246 50.2600082,17.2467152 50.2594803,17.2471072 50.2590518,17.2472887 50.2588899,17.2473825 50.2589031,17.2474603 50.2589831,17.2476183 50.2593547,17.2476129 50.2594891,17.2475362 50.2596838,17.2472527 50.2599602,17.2467975 50.2604295,17.2464185 50.2608597,17.2464899 50.2609763,17.2468294 50.2606692,17.2470729 50.2603893,17.2471375 50.2603275,17.2471712 50.2602965,17.2472164 50.2602548,17.2473568 50.2603397,17.2475969 50.2606721,17.247749 50.2609046,17.248001 50.2611376,17.248148 50.2612709,17.2482863 50.2613782,17.2483511 50.2614436,17.2483235 50.2615255,17.2482463 50.2616572,17.2480242 50.2618683,17.2478889 50.261971,17.2478107 50.2620425,17.2477367 50.2621589,17.2476127 50.2623316,17.2475972 50.2623612,17.2476456 50.2623858,17.2476976 50.2623628,17.247865 50.2622137,17.2481669 50.2619117,17.2483726 50.2617487,17.248518 50.26155,17.2486356 50.2613887,17.2487445 50.2612871,17.2490062 50.2610709,17.2491116 50.2610117,17.2492161 50.2609873,17.2493208 50.2609871,17.2495457 50.2611089,17.2496537 50.2611935,17.2497164 50.2612616,17.249707 50.2613078,17.2496808 50.2613563,17.2490622 50.2620266,17.2483913 50.262842,17.2483891 50.2628801,17.2484246 50.262892,17.2484586 50.2628894,17.2484955 50.2628678,17.2486464 50.2627174,17.2488647 50.2624826,17.2490516 50.2623313,17.2492511 50.2622321,17.2493041 50.2622405,17.2493706 50.2624275,17.2493194 50.2627244,17.2492629 50.2627518,17.2491946 50.2627116,17.249117 50.262635,17.2490619 50.2625574,17.2490036 50.2625489,17.2489674 50.2625896,17.2492027 50.2631161,17.2490889 50.2633527,17.2488945 50.2636067,17.2483568 50.2642292,17.2482661 50.2643047,17.2479735 50.2646013,17.2480494 50.2646035,17.2481463 50.2645049,17.2483173 50.2643107,17.2485224 50.2640879,17.2486648 50.2639426,17.2492103 50.2634245,17.2493776 50.2635996,17.249469 50.2637093,17.2495635 50.2638093,17.2496242 50.2638811,17.2497576 50.2640024,17.2498002 50.2640584,17.2498034 50.264123,17.2497258 50.2642147,17.2493889 50.2645231,17.2493187 50.2645722,17.2492822 50.2646501,17.2493694 50.2646267,17.2495367 50.2644901,17.2499113 50.2641435,17.250191 50.2638348,17.2502299 50.2638112,17.2502761 50.263814,17.2503594 50.2638384,17.2504462 50.2638692,17.2505733 50.2639405,17.2507458 50.2640274,17.2508938 50.2641182,17.2509638 50.2641767,17.2509908 50.2642072,17.2509961 50.2642446,17.250899 50.2643386,17.2507554 50.2644676,17.2507562 50.2644677,17.2507368 50.2644816,17.2507342 50.2644982,17.2507406 50.2645109,17.2507616 50.2645214,17.2507834 50.2645274,17.2508123 50.2645177,17.2508566 50.2644762,17.251223 50.264113,17.2513442 50.2640493,17.2514469 50.2640217,17.2515695 50.2640321,17.2518121 50.2641125,17.2521783 50.2642687,17.2522634 50.2642932,17.252417 50.2642919,17.2525085 50.2642751,17.2528429 50.2640675,17.2531863 50.263766,17.2535173 50.2633963,17.2537354 50.2631407,17.2540208 50.2627926,17.2545882 50.2621964,17.2547191 50.2620661,17.2547525 50.2620192,17.2547489 50.2619939,17.2547133 50.2619833,17.254677 50.2620013,17.2546412 50.2620277,17.2545835 50.2620814,17.2541998 50.2624472,17.2540091 50.2625775,17.253922 50.2626455,17.2535308 50.2630297,17.2531711 50.2633642,17.2530094 50.26354,17.2529572 50.263577,17.2528978 50.2635986,17.2528695 50.2635959,17.252853 50.2635703,17.2528868 50.2634402,17.2529289 50.2631088,17.2529078 50.2629999,17.2528825 50.2627874,17.2528625 50.2626194,17.2534135 50.2620688,17.2537969 50.2616031,17.2533492 50.2619963,17.2531876 50.2621467,17.2527932 50.2625137,17.2527776 50.262454,17.2527169 50.2622226,17.2526289 50.2620454,17.2525332 50.2617667,17.2524748 50.261676,17.2524753 50.2616001,17.253122 50.2609791,17.2529871 50.2609444,17.2522169 50.261632,17.2521585 50.2616582,17.2519902 50.2616425,17.2515075 50.2615618,17.2513768 50.2615534,17.2513484 50.2615367,17.2513284 50.2615154,17.2519316 50.2608087,17.2525033 50.260301,17.2532912 50.2595004,17.2540063 50.2588935,17.2544444 50.2585024,17.2545442 50.2584499,17.2547974 50.2582437,17.2560645 50.2572374,17.2562839 50.2570592,17.2564035 50.2570139,17.256745 50.2570293,17.2569536 50.2570652,17.2571991 50.257145,17.2572311 50.2572112,17.257168 50.2573092,17.2569665 50.2575004,17.2568465 50.2576143,17.256487 50.2578756,17.2559409 50.2583095,17.2554919 50.2586389,17.2554549 50.2586872,17.2554316 50.2587176,17.2553668 50.2587782,17.2549342 50.2591822,17.2534393 50.2604728,17.2530406 50.26089,17.253143 50.260929,17.2532119 50.2608919,17.2535845 50.2605355,17.2537646 50.2603524,17.253901 50.2602549,17.2540845 50.2600665,17.2546857 50.2594932,17.2553983 50.2588897,17.2554654 50.2588371,17.255628 50.2587097,17.2557808 50.2586714,17.2558644 50.2586823,17.2562488 50.2588565,17.2563649 50.2589588,17.2564126 50.2590517,17.2563989 50.2591112,17.2563888 50.259155,17.2562859 50.2592682,17.2557596 50.2597089,17.2555036 50.2599738,17.2555169 50.2599942,17.2555343 50.2600209,17.2555894 50.2600651,17.2559455 50.2603317,17.2561549 50.2604624,17.2561941 50.2605553,17.2560264 50.260737,17.2556885 50.2610112,17.2557564 50.2610242,17.2558823 50.2609392,17.256184 50.2606928,17.2564209 50.2605282,17.2565811 50.2604498,17.2566748 50.260446,17.2567279 50.2604439,17.2568996 50.2603346,17.2570993 50.2601648,17.2572199 50.2600876,17.2574542 50.2599778,17.2575172 50.2599219,17.2575433 50.2598537,17.2575202 50.2597524,17.2574915 50.2596454,17.2575151 50.2596088,17.2577307 50.2593514,17.2580834 50.2590668,17.2585597 50.2586942,17.2590119 50.2583129,17.2589446 50.2583565,17.2587329 50.2585219,17.2580169 50.2590389,17.2574201 50.2595302,17.2573285 50.2595454,17.2572896 50.2595395,17.2572412 50.2595322,17.2571996 50.2594933,17.2571899 50.2594412,17.2571963 50.2593996,17.2573411 50.2592333,17.2574291 50.2590882,17.2574232 50.2590497,17.2573993 50.2590097,17.2573186 50.2589298,17.2571551 50.2587826,17.2571479 50.2587517,17.2571606 50.2587086,17.2572165 50.2586168,17.2573175 50.2585411,17.2579644 50.258092,17.2581647 50.2579331,17.259123 50.2571451,17.2592494 50.2570788,17.2593637 50.2570517,17.259427 50.2570462,17.2594915 50.2570522,17.2595641 50.2570836,17.2596163 50.2571308,17.2596002 50.2572728,17.2595529 50.2573862,17.2595078 50.2574694,17.2592631 50.2578733,17.2591562 50.2580857,17.2591443 50.2581405,17.2591686 50.2582145,17.2591971 50.2582452,17.2593148 50.2582887,17.2593777 50.2583733,17.25995 50.257927,17.26035 50.25698,17.2602 50.256649,17.260521 50.256418,17.2609441 50.2555498,17.259994 50.256214,17.2593 50.255687,17.260106 50.255075,17.2600546 50.2550281,17.260003 50.2550621,17.2598332 50.2550562,17.2597133 50.2550286,17.2596428 50.254951,17.2596003 50.2548526,17.2596125 50.2547776,17.2596662 50.2546812,17.259669 50.2546759,17.25971 50.2545991,17.2597259 50.2545056,17.2596976 50.2544286,17.2596762 50.2543624,17.2596669 50.2543171,17.2596618 50.2542919,17.2596435 50.2542465,17.2596168 50.2541988,17.2595914 50.2541124,17.2595058 50.2539893,17.2594765 50.25386,17.2594761 50.2537534,17.2594796 50.2537516,17.2596064 50.2536858,17.259821 50.2536281,17.2600184 50.2534636,17.2601565 50.253645,17.2603014 50.253647,17.2605225 50.2536379,17.2605311 50.2537827,17.2604859 50.2538566,17.2605694 50.2539992,17.2606396 50.2539007,17.2606799 50.2538048,17.2606731 50.2537483,17.2606843 50.2536018,17.2607508 50.2534357,17.2607508 50.2533483,17.2607426 50.2532691,17.2607253 50.2532024,17.2606793 50.2531545,17.2606634 50.253138,17.2605599 50.253051,17.2605126 50.2529838,17.2604438 50.2528819,17.2603401 50.2527786,17.2601363 50.2525479,17.2601194 50.2525116,17.2601579 50.2524906,17.2601709 50.2524986,17.2602055 50.2525198,17.2602626 50.2525785,17.2603204 50.2526057,17.2603843 50.2526026,17.2604586 50.2525775,17.2607781 50.2524885,17.2608089 50.2524534,17.2608018 50.2524048,17.2607554 50.2523975,17.2606996 50.252407,17.2604044 50.2525149,17.2603802 50.2524959,17.2603829 50.2524786,17.2604037 50.2524319,17.2605334 50.252296,17.2605304 50.2522833,17.2605146 50.2522161,17.2604658 50.2521217,17.2603324 50.25191,17.2603725 50.2518465,17.2603883 50.2518214,17.260491 50.2517503,17.2615284 50.2512637,17.2615839 50.2512397,17.2621799 50.2510249,17.2623707 50.2509937,17.2625979 50.250991,17.2627053 50.2509979,17.2628107 50.250991,17.2629196 50.2509797,17.2629653 50.2509749,17.2630097 50.2509703,17.26306 50.2509489,17.2633748 50.2508146,17.2637352 50.2506705,17.2640014 50.2505799,17.2643619 50.2504629,17.2647284 50.2503977,17.2649374 50.2503857,17.2650517 50.2504009,17.2652107 50.250422,17.2653054 50.2504931,17.2652916 50.2505365,17.265281 50.2505593,17.266563 50.250772,17.266646 50.251144,17.264765 50.251806,17.2644643 50.2524715,17.263494 50.253061,17.261856 50.255068,17.261798 50.255697,17.263288 50.255635,17.2634797 50.2552635,17.2636513 50.2549268,17.2639417 50.2542846,17.2640099 50.254137,17.2640989 50.2539583,17.2641984 50.2537659,17.2642512 50.2537494,17.2643167 50.2536209,17.2648322 50.2535688,17.2649628 50.2535337,17.2651022 50.2535415,17.2654645 50.2535048,17.2656116 50.2533478,17.2658071 50.2530671,17.2659639 50.2529786,17.2659961 50.2529825,17.2660295 50.2529574,17.2660323 50.25299,17.2660652 50.2529984,17.2661394 50.2530593,17.2661196 50.2533787,17.2661706 50.2534588,17.2660728 50.2534536,17.2661177 50.2539671,17.2663069 50.2541487,17.2665772 50.2544548,17.2667635 50.2547711,17.2669355 50.2551715,17.267135 50.2554024,17.2674632 50.2556101,17.2677184 50.2558239,17.2676635 50.2559862,17.2676606 50.2560688,17.2675739 50.2562937,17.2675655 50.2563482,17.2675954 50.2563716,17.2676368 50.2563933,17.2677009 50.2562923,17.2677955 50.256123,17.2678009 50.2561219,17.2678221 50.2561174,17.267897 50.2559413,17.2679814 50.2557901,17.2681901 50.2556095,17.2683225 50.2555807,17.2685836 50.2555349,17.2686211 50.2555172,17.2686196 50.2554972,17.2686232 50.2554923,17.268619 50.2554889,17.2686178 50.2554718,17.2685979 50.2554421,17.2684225 50.2553618,17.2683359 50.2553306,17.2683372 50.2552656,17.2684027 50.2551153,17.2686809 50.2545628,17.268956 50.2540868,17.2690566 50.2539117,17.2690956 50.2538409,17.2692709 50.2538096,17.2694981 50.2538259,17.269766 50.2538709,17.270035 50.253916,17.2701531 50.2539723,17.2700544 50.2541458,17.2697719 50.2545876,17.2694057 50.2551428,17.2688685 50.2559507,17.2688309 50.2560009,17.2688121 50.2560881,17.2688084 50.2560946,17.2687729 50.2562724,17.2686503 50.2566508,17.2686136 50.2568306,17.2685321 50.2570416,17.2684778 50.2571633,17.2684757 50.2572058,17.2684895 50.2572376,17.2685188 50.2572427,17.2685758 50.2572179,17.2686677 50.2570242,17.2687099 50.2568426,17.2687205 50.2567746,17.2687823 50.2565662,17.2688789 50.256317,17.2689169 50.256253,17.2692076 50.2556279,17.2697109 50.2548317,17.2701797 50.2540583,17.2703133 50.2539969,17.2704115 50.254014,17.2705256 50.253996,17.2706555 50.2540522,17.2708211 50.254124,17.2708358 50.254162,17.2708488 50.2541956,17.2708607 50.2543344,17.270756 50.254447,17.2707639 50.2546442,17.2708047 50.2547316,17.2708036 50.2548583,17.2705778 50.2552703,17.2704337 50.2554644,17.2700871 50.2561199,17.2699141 50.2564211,17.269668 50.2571619,17.2694629 50.2577134,17.2694031 50.2579431,17.2694325 50.2579716,17.269478 50.2579619,17.2696257 50.2574537,17.2697995 50.2569218,17.2703327 50.2557166,17.2706754 50.2551501,17.2707193 50.2550661,17.2707973 50.2549861,17.2708214 50.2549435,17.2708775 50.254891,17.2708872 50.2548787,17.2709459 50.2548041,17.2710442 50.2546604,17.2711234 50.2545675,17.2711771 50.254521,17.271247 50.2545205,17.2718534 50.2549133,17.2720067 50.2550053,17.2719494 50.2550627,17.2718116 50.2552006,17.2716041 50.2555217,17.2713909 50.2557159,17.271294 50.2558868,17.2712588 50.2561691,17.2711093 50.2566257,17.270951 50.2569373,17.2709786 50.256962,17.2710202 50.2569417,17.271077 50.2568754,17.2713436 50.2561522,17.2713719 50.2559694,17.2714163 50.2558325,17.2715744 50.255613,17.2717087 50.255447,17.2718269 50.2552848,17.2719918 50.2551561,17.2720519 50.2550848,17.272125 50.2550703,17.2722064 50.255092,17.2726206 50.2553542,17.2726317 50.2553728,17.272672 50.2554405,17.2726874 50.2554892,17.2725845 50.2556024,17.2724602 50.2557043,17.2723788 50.2558288,17.2716156 50.2586624,17.2718144 50.258152,17.2721828 50.2570002,17.272255 50.2568341,17.2724274 50.2563204,17.2725414 50.2562344,17.2726802 50.2562528,17.2729578 50.2562657,17.2732404 50.2563204,17.2733948 50.2563812,17.2734285 50.2564164,17.2734242 50.2564314,17.27341 50.2564811,17.2734277 50.2565298,17.2735052 50.2565347,17.2736836 50.2563697,17.2739629 50.2559184,17.2744285 50.2554122,17.2748781 50.2547623,17.2751114 50.2545576,17.275708 50.2543111,17.2765259 50.2540887,17.2766042 50.2540837,17.2766404 50.254101,17.2766143 50.2541692,17.2764555 50.2544434,17.2762722 50.254776,17.2757022 50.2556029,17.2755992 50.2557676,17.2751806 50.2567643,17.2750453 50.2570864,17.275292 50.2566533,17.2753458 50.2565588,17.27573 50.2558842,17.2757968 50.255887,17.2765868 50.2559197,17.2770282 50.2560136,17.2770678 50.2561075,17.2769516 50.2563485,17.2765211 50.2571829,17.276377 50.2574863,17.2762183 50.2579478,17.2761458 50.2583388,17.2759568 50.2589609,17.2758537 50.2593586,17.2758085 50.2595055,17.2758146 50.2595695,17.275854 50.2596048,17.2759796 50.259186,17.2760215 50.2590183,17.2761181 50.2587454,17.2762702 50.258204,17.2764065 50.2575139,17.2771394 50.2563008,17.2773123 50.2559966,17.2773232 50.2559774,17.2776303 50.256005,17.2781515 50.2560788,17.2783085 50.2561241,17.2783161 50.2561263,17.2781366 50.2563488,17.2777487 50.2570532,17.2775239 50.2575321,17.277435 50.2576882,17.277402 50.2578559,17.2772088 50.2585432,17.2772143 50.2585896,17.2772221 50.2585887,17.2772155 50.2586155,17.2772256 50.2585883,17.2772444 50.2585861,17.2772799 50.2585478,17.2773011 50.2584651,17.2775185 50.2578037,17.2775669 50.2576026,17.2776607 50.2574682,17.2777471 50.2572463,17.2777718 50.2571542,17.2778501 50.2570522,17.2780107 50.2567548,17.278356 50.256342,17.2784096 50.2562652,17.2784601 50.2562082,17.2785065 50.2561777,17.2785658 50.2561161,17.2786451 50.2560448,17.2786504 50.25604,17.2786947 50.2560134,17.2787727 50.2559883,17.2792725 50.2558275,17.2798087 50.2557053,17.2798864 50.2556477,17.2799499 50.2555708,17.2800241 50.2554615,17.2801217 50.2554235,17.2810507 50.2551993,17.2811143 50.255196,17.2811444 50.2552237,17.2811558 50.2552612,17.2807904 50.2558081,17.2797449 50.2573381,17.2796725 50.257506,17.2797138 50.2576125,17.2796404 50.2578692,17.2793029 50.2587544,17.2792821 50.2588376,17.2794051 50.2587977,17.279455 50.2587347,17.2798552 50.2578516,17.2798697 50.2575718,17.2801029 50.2570643,17.280564 50.2563413,17.2813717 50.2552348,17.2814233 50.2551976,17.2815021 50.2551695,17.2817701 50.255174,17.2819493 50.255236,17.2820176 50.2552955,17.2821144 50.2553525,17.2817429 50.2560824,17.2812116 50.2568636,17.2809973 50.2573309,17.2805722 50.2581668,17.2804471 50.2584935,17.2804907 50.2585385,17.2805142 50.2585419,17.2805851 50.2584913,17.2806423 50.2584177,17.2809004 50.2577867,17.281162 50.257281,17.2812567 50.2572245,17.2813664 50.2572306,17.2815102 50.2572849,17.2817897 50.2572819,17.2818745 50.2573078,17.2819266 50.257367,17.2819476 50.2574667,17.2819457 50.2575722,17.2816669 50.2582735,17.2813576 50.2590077,17.2812889 50.2593223,17.2812334 50.2595185,17.2812708 50.2595692,17.2813146 50.2595784,17.2813414 50.2595672,17.2814865 50.2591808,17.2817483 50.258645,17.2817924 50.2585729,17.281916 50.2584905,17.2820306 50.2584075,17.2821064 50.2583432,17.282187 50.2582869,17.2822768 50.25821,17.2824264 50.2580947,17.2825375 50.2580154,17.2826381 50.2579825,17.2827366 50.2580113,17.2827521 50.2580555,17.2826015 50.2584342,17.2824709 50.2587369,17.2823353 50.2588937,17.2822064 50.2590271,17.2821511 50.2590814,17.2821247 50.2591576,17.2821389 50.2593166,17.2822467 50.2595291,17.2822465 50.2596078,17.2822202 50.2596958,17.2822047 50.25973,17.2821359 50.2599286,17.2819712 50.2603416,17.2819043 50.2605166,17.2818867 50.2605796,17.2819153 50.2606467,17.2819624 50.2606516,17.2820069 50.2606181,17.2821668 50.2602402,17.2823067 50.2598634,17.2823529 50.259772,17.2824306 50.2597347,17.2824932 50.259756,17.2825345 50.2598373,17.2826109 50.2599631,17.2826892 50.2600688,17.2829524 50.2604092,17.283015 50.2605617,17.2829888 50.2607744,17.2828982 50.2609703,17.2828428 50.2611374,17.2827199 50.2614475,17.2827137 50.2614884,17.2826726 50.2615799,17.2826134 50.2616338,17.2825268 50.2616513,17.2824599 50.261697,17.2824349 50.2617518,17.2824567 50.262013,17.2824612 50.2621924,17.2824116 50.2625317,17.2822286 50.2631597,17.2821657 50.2633104,17.2821418 50.2634452,17.2821773 50.2635453,17.2822058 50.2635548,17.2822413 50.2635379,17.282265 50.263469,17.2822723 50.2634577,17.2826079 50.2623914,17.2827127 50.2619681,17.282841 50.261549,17.2828783 50.2614917,17.2829375 50.2614491,17.2829641 50.2614466,17.2830136 50.2614666,17.2831028 50.261527,17.2833994 50.261862,17.2834624 50.2622201,17.2834248 50.2623779,17.2832726 50.2628531,17.2830719 50.2634389,17.2831139 50.2634266,17.2830817 50.2635144,17.2830602 50.2636093,17.2830601 50.2636093,17.2830501 50.2635994,17.2830179 50.263591,17.2829712 50.2637163,17.282865 50.263948,17.2828196 50.2641412,17.2827685 50.2642897,17.2827239 50.264386,17.2827097 50.2644188,17.2826774 50.2644962,17.2826518 50.2646255,17.2826061 50.2646775,17.2825235 50.2646806,17.2824738 50.2646888,17.2824599 50.2647272,17.2824554 50.2648018,17.2824276 50.2648814,17.2824218 50.2649512,17.2823982 50.2650539,17.2823962 50.2651395,17.2823337 50.2654075,17.2822886 50.2655257,17.2822593 50.2656051,17.2822008 50.2656565,17.2821883 50.2656583,17.2813717 50.2657412,17.2819717 50.2661405,17.2821451 50.2659268,17.2824124 50.2657343,17.2825605 50.2657272,17.282841 50.2657721,17.2831167 50.2659034,17.28333 50.265923,17.2833702 50.2659111,17.283612 50.2657533,17.2837347 50.2656708,17.2839346 50.2655353,17.2842052 50.265389,17.2837869 50.2660806,17.2840365 50.2661917,17.2842984 50.2662523,17.2846496 50.2659329,17.2847106 50.2658167,17.2847132 50.2656137,17.2847586 50.2655058,17.2848789 50.2652773,17.285108 50.265153,17.2852922 50.2650616,17.2854586 50.264892,17.2858487 50.264376,17.2860489 50.2643114,17.2864335 50.2642843,17.2868011 50.2641725,17.2871083 50.2640632,17.2871738 50.2640931,17.2871828 50.2641645,17.286881 50.2646925,17.2867632 50.2649587,17.2868046 50.2650192,17.2868502 50.2650338,17.2871087 50.264702,17.2872304 50.2647436,17.2873053 50.2646327,17.2874183 50.2644673,17.2872776 50.2644105,17.2874669 50.2641324,17.2876343 50.2640208,17.2879009 50.2639153,17.2880842 50.2638304,17.288207 50.2637481,17.2882569 50.2635079,17.2882952 50.2633604,17.2884381 50.2632195,17.2888944 50.2625382,17.2889932 50.2622872,17.2888267 50.2621539,17.2887087 50.2620054,17.2887018 50.2618767,17.288709 50.2617287,17.2886979 50.2616058,17.2888531 50.261249,17.2889342 50.2610195,17.2889776 50.2608966,17.2890202 50.2608485,17.2892467 50.2605925,17.2892514 50.2604067,17.2893611 50.2601706,17.2896641 50.2596291,17.2898419 50.2592313,17.2900205 50.2588784,17.2900928 50.2587618,17.2903765 50.2588593,17.2906317 50.2589586,17.2915617 50.2592506,17.2924053 50.2595901,17.2925134 50.2596288,17.2926448 50.2597229,17.2927131 50.2596869,17.2928053 50.2596995,17.2939145 50.2602209,17.2942567 50.2604062,17.2943451 50.2605036,17.2944499 50.2605714,17.2945721 50.2606047,17.2947473 50.260603,17.2948183 50.2606138,17.2953996 50.2608665,17.2956753 50.2610396,17.2957225 50.2610692,17.29589 50.2612389,17.2960164 50.2614508,17.2960604 50.261604,17.2960677 50.2617371,17.2961498 50.2618238,17.2967873 50.2620235,17.2970285 50.2620768,17.297111 50.2621082,17.2971472 50.2621475,17.2970975 50.2622387,17.2970844 50.2622628,17.296999 50.262375,17.2968845 50.2625265,17.2968789 50.2625413,17.2968345 50.2626588,17.2968699 50.2627487,17.2971074 50.2628351,17.2973433 50.2629594,17.2973952 50.26302,17.2975291 50.2631708,17.297553 50.2632536,17.2975409 50.2633594,17.2976051 50.263592,17.2976135 50.2637479,17.2975345 50.2639678,17.2974326 50.2641718,17.2973393 50.2642924,17.2972963 50.2644432,17.2970927 50.2648865,17.2967208 50.2654609,17.2966245 50.2654581,17.2965342 50.2654283,17.2965809 50.2654861,17.2965985 50.2655157,17.2966265 50.2655426,17.2966983 50.2656618,17.2966884 50.2658446,17.2961657 50.2665457,17.2958343 50.2669512,17.2958204 50.2669697,17.295928 50.2670167,17.2960912 50.2670684,17.2963578 50.2670729,17.2965174 50.2670478,17.2966347 50.2670348,17.2967088 50.2670701,17.2967334 50.267194,17.2967817 50.267294,17.296834 50.2672896,17.2968977 50.2672376,17.2969956 50.2671444,17.2972085 50.2670278,17.2973799 50.2668704,17.2973193 50.2664383,17.2973801 50.2663019,17.2975044 50.266218,17.2976179 50.2662813,17.2976643 50.2664194,17.2977152 50.2667081,17.2977826 50.2667608,17.2978827 50.266757,17.2980442 50.2665862,17.2982799 50.2664507,17.2983331 50.2664923,17.2983606 50.2665405,17.2983887 50.2667742,17.2983183 50.2670693,17.2975122 50.2680411,17.2969271 50.2686012,17.2965086 50.2689019,17.2961821 50.269149,17.2956198 50.2694979,17.2953021 50.2696837,17.295107 50.2697445,17.2949398 50.2697698,17.2942809 50.269831,17.2938182 50.2699095,17.293413 50.2699295,17.2931215 50.2699011,17.2930379 50.2699071,17.2930363 50.2699071,17.2928105 50.2699042,17.2927706 50.2698933,17.2932044 50.2696527,17.2931986 50.2696279,17.2930508 50.269716,17.292987 50.2697378,17.2929336 50.2697358,17.2928976 50.2697171,17.2927269 50.2695265,17.2926379 50.2693818,17.2925663 50.2693248,17.2925043 50.2693155,17.2923756 50.2693091,17.2922289 50.2693378,17.2921101 50.2693953,17.2919782 50.2695468,17.2917642 50.2697003,17.2915226 50.2699325,17.2911751 50.2700784,17.2910093 50.2701792,17.2909113 50.2702647,17.2907842 50.2703756,17.290587 50.2705055,17.2904294 50.2705251,17.2903414 50.270536,17.2901794 50.2705357,17.2901043 50.2705255,17.2900642 50.2705172,17.2899709 50.2704936,17.2899194 50.2704925,17.2898808 50.2705014,17.2898192 50.2705477,17.2898066 50.270554,17.2890326 50.2709459,17.2887207 50.2712449,17.288543 50.2714785,17.288354 50.2716692,17.2881659 50.271819,17.2879794 50.2719408,17.2878119 50.2720305,17.2875262 50.2722562,17.2873094 50.2724186,17.2870912 50.2725177,17.2865835 50.2725379,17.2863421 50.2725858,17.2862097 50.2726217,17.2860938 50.2726875,17.2854077 50.273242,17.2852961 50.2733442,17.2851875 50.2733996,17.2850935 50.2734334,17.2849886 50.2734096,17.2849061 50.2733586,17.2848726 50.2733438,17.2848364 50.2733461,17.2847902 50.2733558,17.2847036 50.2733836,17.2845458 50.2734124,17.2843141 50.2734105,17.2842141 50.2734202,17.2840721 50.2734272,17.284014 50.2734385,17.2839502 50.2734607,17.2839111 50.2735076,17.2839015 50.2735641,17.2839072 50.2735966,17.2838614 50.2737483,17.2837803 50.2738326,17.2836888 50.2739037,17.2833206 50.274068,17.2834849 50.274375,17.2837651 50.2742795,17.2843161 50.2746018,17.2847831 50.2743511,17.2850166 50.2738258,17.2855303 50.2735154,17.2860865 50.2736111,17.2866171 50.273091,17.2867917 50.2729233,17.2870133 50.2727756,17.2872671 50.2727063,17.2874733 50.272672,17.2879782 50.2725875,17.2882367 50.272538,17.2885777 50.2725208,17.2890323 50.2725433,17.289307 50.2726167,17.2895584 50.2727433,17.2897732 50.2727194,17.2900445 50.2725876,17.2904036 50.2722059,17.2904903 50.271854,17.2904946 50.2717843,17.2904776 50.2716541,17.2905048 50.2714136,17.2906101 50.2711258,17.2909094 50.2707644,17.29112 50.2705502,17.2913658 50.2704095,17.2916508 50.2703255,17.2918828 50.2702742,17.2921418 50.270231,17.2926288 50.2701829,17.2934767 50.2700754,17.2938869 50.2700463,17.2947582 50.2699344,17.2949179 50.2699228,17.2952305 50.269884,17.2956046 50.2697413,17.2961491 50.2693693,17.2967124 50.2690123,17.2973093 50.2686231,17.2977118 50.2682596,17.2978967 50.268068,17.2979788 50.2680627,17.2983623 50.2681392,17.2984223 50.2681361,17.2992697 50.2672827,17.2996689 50.2668599,17.2998302 50.2666223,17.2999646 50.2664581,17.2998314 50.2663544,17.2996744 50.2662939,17.2995591 50.266283,17.2993895 50.2663848,17.299245 50.2664374,17.2991866 50.2664915,17.2991232 50.2665161,17.2990668 50.2665237,17.2990364 50.2664987,17.2989982 50.266457,17.2989828 50.2663829,17.2989201 50.2662719,17.2987993 50.2661382,17.2987204 50.2660925,17.2985677 50.2659862,17.2982067 50.2657863,17.2981097 50.2656844,17.2980371 50.2655798,17.2979313 50.265444,17.2979009 50.2652746,17.2979783 50.2650925,17.2980227 50.2648777,17.2982551 50.2645491,17.2983771 50.264471,17.2984563 50.2644328,17.2985689 50.264428,17.2986915 50.2644061,17.2987828 50.2642982,17.2988358 50.2642203,17.2989314 50.2641809,17.2990935 50.2642175,17.299208 50.2642486,17.299365 50.2643183,17.2994559 50.264347,17.2995969 50.26442,17.2996159 50.26447,17.2996022 50.2645571,17.2995528 50.2646535,17.2994569 50.26488,17.2994701 50.2649705,17.2994788 50.2650304,17.299496 50.2650491,17.29955 50.2651081,17.2997021 50.2651638,17.299956 50.265242,17.3001155 50.2653616,17.3001131 50.26545,17.3000654 50.26554,17.2998303 50.2657762,17.2997579 50.2659993,17.2997499 50.2661695,17.2999063 50.266298,17.3000352 50.2663564,17.300252 50.2663488,17.3003791 50.2663673,17.3006404 50.2664291,17.300709 50.2664404,17.3007632 50.2664403,17.3008591 50.2664151,17.3009864 50.2662798,17.3009951 50.2662705,17.3010765 50.2661991,17.3011686 50.2661815,17.3012558 50.2661807,17.3015054 50.266222,17.3016491 50.26629,17.3016873 50.2663323,17.3017011 50.2663714,17.3016976 50.2664269,17.3014993 50.266834,17.3014256 50.267001,17.3014138 50.2670779,17.3014467 50.2671387,17.3015537 50.267272,17.301563 50.2672836,17.3015439 50.2674401,17.3015406 50.2676709,17.3015632 50.2677504,17.3016697 50.2679016,17.3016777 50.2679088,17.3017384 50.2679846,17.3017523 50.2680452,17.3017453 50.2680778,17.3017408 50.2680984,17.3017236 50.2681287,17.3014778 50.2684179,17.3013477 50.2685984,17.3010332 50.2690347,17.3009799 50.2691475,17.3010048 50.2691738,17.3010661 50.269137,17.301148 50.2690402,17.3012475 50.2689797,17.3013255 50.2689702,17.3014621 50.2690411,17.3017455 50.2691864,17.3020122 50.2693212,17.3020334 50.2693608,17.302 50.2694001,17.3019286 50.2694527,17.3016613 50.2695547,17.3014967 50.2696087,17.3014302 50.2696779,17.3014168 50.2697487,17.3014475 50.2698559,17.3016039 50.2700187,17.3018723 50.2701407,17.3021047 50.2701757,17.3024162 50.27014,17.3027727 50.2700765,17.3030068 50.2700558,17.3030286 50.2700879,17.3029674 50.2702384,17.3026518 50.2707022,17.3023539 50.2710954,17.3022736 50.271152,17.3022529 50.2711851,17.3021987 50.2712462,17.301868 50.2715048,17.3014369 50.2719064,17.3014342 50.2719048,17.3013801 50.2719599,17.3012971 50.2720007,17.3012098 50.2720301,17.3011177 50.2720611,17.3009301 50.2721022,17.3003995 50.2723224,17.2990165 50.273035,17.2982914 50.2734566,17.2979069 50.273741,17.2976221 50.2739806,17.2973464 50.2742743,17.2969045 50.2745771,17.2959368 50.2752892,17.2955303 50.2755746,17.2948256 50.2761245,17.2941963 50.2765644,17.2936813 50.2770715,17.2933051 50.2774874,17.2922658 50.2783611,17.2918987 50.2787176,17.2915378 50.2790346,17.2911462 50.2792267,17.2909264 50.2793094,17.2907812 50.2793775,17.2906733 50.2794538,17.2906402 50.2794947,17.2906363 50.2795474,17.2906169 50.2795844,17.2905413 50.2796686,17.2904704 50.2797214,17.2903829 50.2797716,17.290124 50.27984,17.2899216 50.2798751,17.2898285 50.2798857,17.2897577 50.2798812,17.2896733 50.2798355,17.2894954 50.2797611,17.2893981 50.279745,17.2892777 50.2797451,17.2891407 50.2797519,17.2890038 50.2798027,17.2889539 50.2798139,17.288131 50.280327,17.2878794 50.2806353,17.2887799 50.2812824,17.2890788 50.2811471,17.2902965 50.2818963,17.291451 50.282824,17.291696 50.285025,17.29224 50.285309,17.293413 50.2875649,17.2950677 50.2879448,17.2954167 50.2879058,17.2959214 50.2881743,17.296145 50.2880581,17.2962328 50.2880286,17.2963292 50.2880137,17.296411 50.2880189,17.2965013 50.2880357,17.296589 50.288073,17.2969742 50.28826,17.2973209 50.2884274,17.2979624 50.2887209,17.2984847 50.2889365,17.2988794 50.2890924,17.2991733 50.2891797,17.2996861 50.2893738,17.2997978 50.2892602,17.2998935 50.2891629,17.2999786 50.2891141,17.3000396 50.2891076,17.3000531 50.2891062,17.3002056 50.2891321,17.3003337 50.289161,17.3006118 50.2892409,17.3008191 50.2892866,17.3009674 50.2893032,17.3012266 50.2893042,17.301499 50.2892844,17.3016665 50.2892589,17.3018483 50.2892406,17.3020356 50.2892696,17.3022316 50.2893154,17.3023718 50.2893568,17.3024866 50.2894174,17.3025865 50.2894824,17.3027013 50.2896161,17.3030635 50.2898911,17.3032058 50.2899798,17.3032974 50.2900477,17.3033808 50.2900949,17.3036541 50.2902031,17.3039384 50.2903349,17.3040267 50.2903838,17.3040794 50.290435,17.3040858 50.2904941,17.3040519 50.2905769,17.303934 50.2907293,17.3038948 50.2907714,17.3038775 50.290806,17.3038822 50.2908267,17.3038957 50.2908429,17.3041298 50.2909404,17.3042696 50.2910035,17.3044496 50.2910979,17.3049551 50.2913371,17.3053034 50.2912842,17.3056042 50.2913738,17.30625 50.290676,17.306111 50.290063,17.30621 50.2897,17.30595 50.2897,17.3058246 50.2896061,17.3058992 50.289402,17.306113 50.289049,17.3065844 50.2892249,17.3065923 50.2892084,17.3066329 50.2891479,17.3066038 50.2887926,17.3065157 50.2885341,17.3065312 50.2882488,17.3066293 50.288106,17.3067108 50.2880072,17.3067606 50.2879679,17.3068268 50.2879315,17.3068873 50.2878684,17.3069394 50.2878139,17.3071609 50.2876391,17.3078048 50.2873122,17.3080844 50.2871837,17.3096943 50.2862804,17.309724 50.2862015,17.3098196 50.2861028,17.3100275 50.2859795,17.3102137 50.2858965,17.3103203 50.2857352,17.3104253 50.2856578,17.3105662 50.2854382,17.3105468 50.2852807,17.3104865 50.2851414,17.3105198 50.2850071,17.3105298 50.2848235,17.3105865 50.2842466,17.3105908 50.2841345,17.3105974 50.2840365,17.3107768 50.2839882,17.310881 50.2840388,17.311217 50.284124,17.3124008 50.2845427,17.312484 50.2845559,17.3125756 50.2845011,17.3126559 50.2844195,17.3127811 50.2842928,17.3129286 50.2841511,17.313425 50.283588,17.3129139 50.2826074,17.3129068 50.2825972,17.3128228 50.2824326,17.312756 50.2823,17.3129707 50.2822863,17.3130231 50.2822466,17.3137331 50.2822128,17.3143791 50.2821718,17.315129 50.2821171,17.3152841 50.2821169,17.3153468 50.2821349,17.317275 50.282012,17.3181976 50.2831526,17.3184723 50.283348,17.3190293 50.2836272,17.3196539 50.2839621,17.3199673 50.284097,17.3207354 50.2845302,17.3207857 50.2845616,17.3213092 50.2848206,17.3216612 50.2850776,17.3226089 50.285592,17.3233795 50.2858527,17.3242204 50.2862434,17.3244504 50.2862552,17.324611 50.285775,17.3249155 50.286215,17.3249227 50.286213,17.3249584 50.2862649,17.3249646 50.286286,17.3250725 50.2864419,17.3250815 50.2864452,17.3251247 50.2864118,17.3251799 50.2864108,17.3252253 50.2864452,17.3252808 50.2864751,17.3261453 50.2864687,17.328438 50.285559,17.33274 50.279475,17.331178 50.278442,17.3294157 50.2766753,17.328962 50.276221,17.328201 50.274204,17.331133 50.272025,17.33225 50.270807,17.33194 50.270235,17.332346 50.270338,17.332394 50.2702636,17.3323843 50.2702289,17.3324192 50.270158,17.3327631 50.2696682,17.3328431 50.2695889,17.3328253 50.2695878,17.332819 50.2695701,17.3328492 50.26952,17.3328787 50.2694779,17.3329363 50.2694147,17.3329886 50.2693773,17.3330377 50.2693325,17.333069 50.2692594,17.3330661 50.2692025,17.3330637 50.2691811,17.33045 50.26885,17.332725 50.266145,17.3352683 50.2660219,17.3354321 50.2659797,17.3355738 50.2659471,17.3356044 50.2659861,17.3355925 50.2660062,17.3356774 50.2660021,17.3357586 50.2659091,17.3359448 50.2658892,17.3362981 50.2658916,17.3364722 50.2659143,17.3365771 50.2659471,17.3365753 50.2659586,17.337001 50.265938,17.337869 50.265685,17.338203 50.265361,17.33805 50.265195,17.3388131 50.2654348,17.3388344 50.2654246,17.3389372 50.2654247,17.3391535 50.2654664,17.3392263 50.2654766,17.3393747 50.2655431,17.3394457 50.2655761,17.3396038 50.2656447,17.3398948 50.2657416,17.3401331 50.2658234,17.340214 50.2658751,17.3405258 50.2659731,17.340645 50.2659285,17.3407177 50.2658431,17.3408776 50.2657466,17.3409825 50.2656782,17.3410751 50.2656522,17.341089 50.265643,17.3410929 50.2656472,17.341697 50.26595,17.342487 50.265727,17.34264 50.2656815,17.3426824 50.265629,17.3427343 50.2655844,17.3427994 50.2655551,17.3428908 50.2655563,17.3429999 50.2655744,17.343445 50.265442,17.342795 50.264966,17.342927 50.26475,17.343656 50.26515,17.344086 50.264624,17.342725 50.264246,17.3379 50.26397,17.337575 50.263753,17.337388 50.263639,17.33714 50.263251,17.335205 50.260993,17.335 50.26004,17.335442 50.260075,17.335141 50.25951,17.333711 50.258807,17.333211 50.259149,17.333193 50.258464,17.332467 50.258206,17.331994 50.258082,17.332258 50.257974,17.331766 50.257794,17.330811 50.25767,17.326425 50.255562,17.321332 50.254645,17.319259 50.253257,17.315694 50.251529,17.316648 50.25147,17.315212 50.25065,17.314695 50.25065,17.313298 50.249707,17.313415 50.249634,17.313394 50.249618,17.313299 50.249596,17.313081 50.2496,17.311544 50.24895,17.31135 50.248689,17.3116398 50.2480468,17.3119727 50.2478538,17.3124113 50.2481674,17.3130236 50.248392,17.3134253 50.2482798,17.315261 50.249286,17.314912 50.250161,17.314457 50.250069,17.316666 50.251385,17.318522 50.252344,17.319293 50.252963,17.321473 50.254143,17.321898 50.254327,17.322126 50.25439,17.322544 50.254425,17.3234667 50.2547477,17.324294 50.2547443,17.324893 50.2549,17.32655 50.25515,17.330625 50.257145,17.331486 50.256198,17.333046 50.253299,17.333435 50.253392,17.334848 50.252289,17.3361357 50.2520144,17.3361928 50.2519661,17.3362013 50.2519389,17.336091 50.250949,17.3373 50.25103,17.3373117 50.2508684,17.3373102 50.2507447,17.3372982 50.2506361,17.3373008 50.2505064,17.3373117 50.2504718,17.3373332 50.2504544,17.3373403 50.2503187,17.3373236 50.2502819,17.3373482 50.2501788,17.3373151 50.2499997,17.3372887 50.249933,17.337219 50.2498441,17.3372518 50.2498435,17.3373162 50.2498502,17.3373574 50.2498528,17.3369526 50.2496547,17.3369374 50.2496528,17.3369111 50.249638,17.3369072 50.2496325,17.3369 50.249629,17.3368996 50.2496219,17.3368875 50.2496049,17.3368556 50.2494925,17.3368812 50.2492782,17.336867 50.249012,17.3368494 50.2488663,17.3368169 50.248838,17.3367792 50.2488172,17.3367148 50.2488105,17.3358885 50.248811,17.33585 50.2487954,17.3357976 50.2487632,17.3357568 50.2487081,17.3342641 50.2481355,17.3339158 50.2480809,17.3336703 50.2480193,17.3332053 50.2479376,17.3330045 50.2479331,17.3328988 50.2479246,17.3328128 50.2479065,17.332675 50.247859,17.3324732 50.2477695,17.332253 50.2476806,17.3320945 50.2476399,17.3319966 50.2476086,17.330393 50.247326,17.33047 50.246963,17.3318561 50.2466803,17.3318868 50.2466061,17.3319136 50.2464958,17.331955 50.2464099,17.331947 50.2463301,17.3319511 50.2462692,17.3319147 50.2461761,17.3318695 50.2461237,17.3318565 50.2461143,17.3318492 50.2461012,17.331851 50.2460835,17.3318394 50.246064,17.3318321 50.2460104,17.3318318 50.2459749,17.33177 50.246055,17.3311288 50.2459846,17.330788 50.246019,17.3305826 50.2460248,17.330454 50.2459925,17.3302174 50.2459293,17.3298639 50.2458935,17.3297705 50.2458769,17.3296426 50.2458124,17.329494 50.2456929,17.3293524 50.245582,17.3292292 50.2454746,17.3290777 50.2453512,17.3289164 50.2451631,17.328863 50.245025,17.3286151 50.2445875,17.3285883 50.244556,17.3283573 50.2441843,17.3281085 50.2437658,17.3280366 50.2436683,17.3280299 50.2436303,17.3280555 50.2435997,17.328008 50.24352,17.3286221 50.2434143,17.3287875 50.243372,17.3290193 50.2433303,17.3290654 50.243338,17.330268 50.243131,17.332052 50.243275,17.3326772 50.2430679,17.3328221 50.2429978,17.332924 50.2429121,17.333137 50.2428181,17.3333846 50.242728,17.3336797 50.242696,17.333854 50.2426781,17.336822 50.241695,17.336709 50.2416035,17.3366903 50.2415987,17.3366325 50.2415807,17.3365899 50.2415644,17.3365396 50.2415432,17.3364987 50.2415162,17.3363715 50.2414639,17.3360937 50.24131,17.3358974 50.2411477,17.3358171 50.2410839,17.3357352 50.24103,17.335674 50.2409701,17.3356388 50.2409236,17.3356156 50.2408915,17.3356063 50.2408602,17.3355807 50.2408342,17.335524 50.2408089,17.335451 50.2407799,17.3351233 50.240547,17.334991 50.2404546,17.3349781 50.2404285,17.3349813 50.240417,17.335028 50.2403974,17.3351826 50.2403683,17.3350716 50.2402786,17.3349756 50.2403021,17.3348898 50.2403064,17.3348011 50.2402882,17.3347217 50.2402362,17.3345698 50.2401213,17.3343054 50.2399259,17.3339922 50.2396747,17.3338621 50.2395506,17.3338387 50.2395193,17.3338375 50.2394904,17.3338677 50.2394679,17.333925 50.2394525,17.3340279 50.2394339,17.333699 50.2391678,17.3336936 50.2391706,17.3336404 50.239178,17.3335101 50.2391279,17.3334598 50.23907,17.3332592 50.2389083,17.3328918 50.2385206,17.3328799 50.2385049,17.332534 50.238225,17.33249 50.237455,17.331495 50.236585,17.3282567 50.2342729,17.326525 50.233734,17.324235 50.232495,17.322868 50.231556,17.322683 50.230475,17.323799 50.228633,17.324375 50.228251,17.324156 50.228135,17.3230637 50.2285749,17.322962 50.2286409,17.3226499 50.2288208,17.3224092 50.2289384,17.3222696 50.2289836,17.3220163 50.2290294,17.3218671 50.2290569,17.321385 50.229251,17.3209782 50.2293102,17.321393 50.2298344,17.3210402 50.2299624,17.3213375 50.2303289,17.3215104 50.2304822,17.3215511 50.2305716,17.3215451 50.230669,17.321492 50.2307304,17.3213996 50.2307903,17.3213015 50.2308297,17.3212531 50.2308929,17.3212685 50.2309498,17.3214396 50.2310531,17.3219709 50.231223,17.3220264 50.2312393,17.3222098 50.2313122,17.3220528 50.2314147,17.3216361 50.2317038,17.321325 50.231862,17.3211 50.231818,17.3208174 50.2318334,17.3207834 50.2318667,17.3205154 50.2318498,17.3204748 50.231852,17.320068 50.2319076,17.319755 50.2319492,17.3194303 50.231941,17.3192014 50.2318712,17.3191538 50.2318387,17.3178789 50.2315073,17.3177341 50.2314693,17.3175332 50.2314295,17.3171633 50.2313347,17.316991 50.2313167,17.312596 50.231868,17.3125915 50.2318845,17.3123342 50.232832,17.3118996 50.2330344,17.3111421 50.2327911,17.3104888 50.23253,17.3102838 50.2320122,17.3090193 50.2322763,17.3087702 50.232361,17.3083752 50.2324801,17.3079685 50.2326764,17.3071647 50.2325177,17.3071479 50.2325166,17.3070213 50.2325158,17.3068268 50.2325261,17.3067412 50.2325272,17.3065765 50.2325375,17.3065268 50.2325278,17.3063668 50.2325231,17.3061741 50.2325133,17.3056417 50.2323743,17.3055538 50.2323373,17.3044465 50.232117,17.3043437 50.2320987,17.3042868 50.2320919,17.3042867 50.2320915,17.3036329 50.2319769,17.3029944 50.2318434,17.3022855 50.2317009,17.3021713 50.2316611,17.3019792 50.2316226,17.2994698 50.2308057,17.2970602 50.2302983,17.2970548 50.2303242,17.2970456 50.2303472,17.2970228 50.2303493,17.2969873 50.2303416,17.2967998 50.2302701,17.296606 50.2302027,17.2962383 50.2301264,17.2962175 50.2301284,17.2961192 50.2301448,17.2960651 50.2301576,17.2960092 50.230155,17.2947191 50.230385,17.2937613 50.2301031,17.2951533 50.2297192,17.293138 50.22905,17.2923838 50.2290241,17.2917991 50.229209,17.2916056 50.228919,17.2898374 50.2284927,17.286675 50.228145,17.2830403 50.2271767,17.2804371 50.2271194,17.279726 50.2271022,17.279225 50.227067,17.2771996 50.2262326,17.2753087 50.225297,17.2742431 50.2246425,17.2736642 50.2238258,17.2728632 50.2224428,17.2728982 50.2217951,17.2738133 50.2205477,17.2739883 50.2198954,17.2739274 50.219413,17.2733386 50.2188783,17.2721891 50.2183121,17.2714744 50.2180776,17.2705737 50.2179177,17.2679246 50.2181656,17.2663883 50.2184591,17.2631613 50.2194182,17.2617782 50.2195845,17.2592891 50.2195113,17.2556387 50.2197334,17.2548564 50.2195376,17.2542308 50.2191368,17.252314 50.217498,17.250927 50.21717,17.249472 50.216162,17.249113 50.215397,17.250339 50.215149,17.2507 50.214749,17.250213 50.214116,17.247548 50.212803,17.245358 50.2112,17.2453048 50.211425,17.245095 50.212294,17.2448796 50.2123197,17.2448529 50.2123464,17.2451854 50.2127438,17.2452984 50.2128268,17.2456609 50.2131869,17.2457638 50.2133389,17.2457937 50.2134005,17.245784 50.2134037,17.2457809 50.2134466,17.2457773 50.2134513,17.2459314 50.2136354,17.2456643 50.2136426,17.2455442 50.2138122,17.2455194 50.2138618,17.2454468 50.2139935,17.245418 50.2139903,17.2454066 50.2140065,17.2451731 50.2139576,17.2442122 50.2138047,17.243621 50.2136328,17.2433924 50.213585,17.243351 50.2135823,17.243313 50.2135727,17.243026 50.2137044,17.2430213 50.2137112,17.2429843 50.2137235,17.2428923 50.2137657,17.2428284 50.2138109,17.2426591 50.2138727,17.2422941 50.2140402,17.2420996 50.2140709,17.2419283 50.2141409,17.2418248 50.2141181,17.2418137 50.2141161,17.2417519 50.2141259,17.2397548 50.213694,17.2397522 50.2132517,17.2391179 50.2131817,17.238932 50.2131594,17.2383965 50.2130559,17.2370011 50.2133485,17.2366956 50.2134606,17.2359301 50.2137413,17.2348371 50.2142404,17.2347725 50.2142127,17.2346182 50.2141465,17.234346 50.214226,17.234002 50.2144,17.2335539 50.2139358,17.2334859 50.2139291,17.2333898 50.2138867,17.2333239 50.2138121,17.2332387 50.2137624,17.2331651 50.2137197,17.2330286 50.2136288,17.2328495 50.2134131,17.2327737 50.2132484,17.2327204 50.2131564,17.2326677 50.2131061,17.2326213 50.2130878,17.2324974 50.2130682,17.2304031 50.2132683,17.2303802 50.2134961,17.2308187 50.2136236,17.2309091 50.213428,17.2317012 50.2134694,17.2320319 50.2144298,17.2317016 50.2144832,17.2312785 50.2146764,17.2316079 50.2149739,17.2317756 50.2151458,17.2321556 50.2153142,17.2328617 50.2152766,17.2333047 50.2155202,17.2338592 50.2158754,17.2341489 50.2159196,17.2345396 50.2162291,17.2342977 50.216321,17.2353686 50.2169455,17.2355564 50.2168849,17.2363139 50.2173675,17.2366634 50.2172064,17.2372723 50.2172545,17.2377985 50.2172329,17.2378848 50.2173981,17.2379407 50.2176023,17.2373475 50.2178462,17.2366452 50.2179669,17.2366312 50.218376,17.23795 50.220194,17.235554 50.220225,17.2355074 50.2213867,17.234904 50.2217203,17.2343115 50.2219548,17.233633 50.221761,17.233475 50.22175,17.231987 50.221619,17.2326545 50.2222247,17.230125 50.221985,17.22957 50.2217,17.230909 50.222975,17.2305751 50.2230199,17.2303852 50.2229545,17.2302027 50.2225527,17.2298084 50.22252,17.2295382 50.2226602,17.2291439 50.223146,17.228001 50.223124,17.228371 50.223589,17.228638 50.22345,17.229381 50.224787,17.229411 50.224899,17.229442 50.224961,17.229575 50.224883,17.229803 50.225374,17.2292426 50.2255593,17.230241 50.226252,17.230012 50.226628,17.2287018 50.2259344,17.2282988 50.2260254,17.228504 50.226641,17.2294805 50.2272326,17.2299822 50.2277184,17.2296485 50.2279332,17.229325 50.227849,17.227975 50.226813,17.2277172 50.2263067,17.2264175 50.2247465,17.226741 50.22446,17.225501 50.223616,17.225755 50.223378,17.2213343 50.2228206,17.2219432 50.2222082,17.2229749 50.2223215,17.2230576 50.2220305,17.2240985 50.2222226,17.224248 50.2221382,17.2245935 50.2219432,17.223115 50.220803,17.222857 50.22061,17.222689 50.220469,17.222994 50.220204,17.221917 50.2195522,17.2225261 50.2189064,17.224475 50.2185724,17.2232917 50.218461,17.2236126 50.218186,17.2242216 50.2180691,17.2262498 50.2178375,17.2228393 50.2177485,17.22096 50.2186169,17.219898 50.219604,17.2205805 50.2197848,17.220787 50.220102,17.221908 50.220991,17.221986 50.221364,17.221752 50.221536,17.2211782 50.2217509,17.2206976 50.2215997,17.2203603 50.2213499,17.220062 50.222141,17.218901 50.222088,17.219327 50.221486,17.219189 50.22155,17.218075 50.221548,17.216952 50.220929,17.2167225 50.2209321,17.2162563 50.2212066,17.2156675 50.2214706,17.2141463 50.22244,17.213798 50.22255,17.213626 50.222662,17.213357 50.222988,17.214022 50.222857,17.214102 50.223239,17.213548 50.223427,17.214455 50.223416,17.21506 50.224339,17.215975 50.224033,17.215837 50.224199,17.216295 50.22403,17.217401 50.225425,17.21625 50.225724,17.2164 50.226123,17.215998 50.22615,17.21584 50.225819,17.215145 50.225966,17.2155264 50.2274083,17.215475 50.229275,17.213412 50.229789,17.2124552 50.2299841,17.2119007 50.2301669,17.2113435 50.230307,17.2099185 50.2300131,17.2098304 50.2300907,17.2096837 50.2302935,17.2111291 50.2305998,17.2117856 50.2306352,17.2126785 50.2305429,17.2127113 50.2304617,17.2140868 50.2306186,17.2149129 50.230465,17.215738 50.2307227,17.2168712 50.2311257,17.2170195 50.2314542,17.2164153 50.2317617,17.2157443 50.2313117,17.2157519 50.2308195,17.2154014 50.2310274,17.2153539 50.2314338,17.2151915 50.2315614,17.2149073 50.2319107,17.2112622 50.2321929,17.2106527 50.2326075,17.2096477 50.2325804,17.2087629 50.2326303),(17.2159 50.23055,17.218775 50.229448,17.219579 50.229442,17.219743 50.229665,17.217025 50.230263,17.216298 50.23055,17.2159 50.23055),(17.2173374 50.2416593,17.219537 50.240536,17.219611 50.240024,17.222261 50.238653,17.222608 50.239046,17.2175473 50.2418243,17.2173374 50.2416593),(17.2244434 50.2260202,17.2248157 50.2257108,17.2255326 50.2260992,17.2252744 50.226363,17.2257825 50.2266748,17.2256576 50.226792,17.2244434 50.2260202),(17.2362267 50.2446669,17.236412 50.244545,17.2365605 50.2442914,17.236893 50.244136,17.238225 50.244479,17.239083 50.244361,17.2380165 50.2450739,17.237703 50.245148,17.23768 50.245141,17.236839 50.244803,17.2365648 50.2450285,17.23625 50.244949,17.2362267 50.2446669),(17.2373358 50.2379637,17.2373919 50.2378347,17.237448 50.2378507,17.2374798 50.2378573,17.237743 50.2379118,17.2378822 50.2380115,17.2377534 50.2381417,17.2375165 50.2381776,17.2373545 50.2381059,17.2373358 50.2379637),(17.2442757 50.255843,17.2442826 50.2558041,17.2442867 50.2557814,17.2443569 50.2556829,17.2445871 50.2555069,17.2449058 50.2552346,17.2452673 50.2550011,17.2455409 50.2548361,17.2458243 50.2546806,17.2458521 50.2546653,17.2460642 50.2545334,17.2462516 50.2543972,17.2464255 50.2543207,17.2465967 50.2542341,17.246713 50.2543381,17.2468182 50.2544957,17.2468723 50.2546464,17.2468766 50.2548003,17.246798 50.2548892,17.2466503 50.2550144,17.2463881 50.2552334,17.2461542 50.2555058,17.2460035 50.2556674,17.245884 50.2557722,17.2456296 50.2559619,17.2455215 50.256096,17.245424 50.2561521,17.2453036 50.2561652,17.2451975 50.2561674,17.2451069 50.2561526,17.245007 50.2561517,17.2449021 50.2562078,17.244873 50.2562458,17.2448462 50.2562667,17.2447988 50.2563037,17.2446696 50.2563099,17.2445811 50.2562867,17.2445098 50.2562681,17.2444047 50.256237,17.2443231 50.2560818,17.2443034 50.2559459,17.2442757 50.255843),(17.2464594 50.2563606,17.2464878 50.2562776,17.2467621 50.2559606,17.2470371 50.2556886,17.2474613 50.2554062,17.2483437 50.2545985,17.2484235 50.2545223,17.2489442 50.2540251,17.2494996 50.2536114,17.2497853 50.2533986,17.2501295 50.2530782,17.2505398 50.2527222,17.2505471 50.2527258,17.2516616 50.2532743,17.2523127 50.2528009,17.2526875 50.2525918,17.2530926 50.2523601,17.2532956 50.2522502,17.2534518 50.2521427,17.2539938 50.2519092,17.2543409 50.251774,17.25455 50.2516843,17.254775 50.2516047,17.2549879 50.2515948,17.2552013 50.2515813,17.2553898 50.2515201,17.2554422 50.2514926,17.2555048 50.2514597,17.2556628 50.251443,17.2557166 50.2514464,17.2557594 50.2516349,17.2557697 50.2516641,17.2558582 50.2519158,17.2558624 50.2519731,17.2558635 50.251989,17.2556666 50.2520889,17.2554653 50.2521909,17.2554356 50.2522692,17.2559618 50.252665,17.2560168 50.2527281,17.2559742 50.2527561,17.2558992 50.2528055,17.2545028 50.2535822,17.2544611 50.2535883,17.2538652 50.2531926,17.253705 50.253129,17.2536701 50.2531151,17.253471 50.253191,17.2527771 50.253686,17.2526831 50.2537335,17.2526517 50.2537494,17.2514662 50.2534017,17.2514104 50.2534113,17.2508871 50.2537622,17.2506218 50.2540178,17.2493627 50.2549415,17.2485299 50.2555572,17.2482451 50.2556918,17.2481598 50.2557912,17.2479678 50.2560285,17.2478594 50.2561764,17.2477042 50.2562763,17.2475882 50.2563238,17.2474092 50.2564771,17.2472663 50.2565978,17.2471927 50.2568367,17.2470321 50.257071,17.2469368 50.2571328,17.2469199 50.2571438,17.2468016 50.2571562,17.2467047 50.25713,17.2467047 50.2570801,17.2466716 50.2568933,17.2466112 50.2567683,17.2465894 50.2567233,17.246524 50.2565444,17.2464594 50.2563606),(17.2481061 50.2592478,17.2483418 50.259,17.2485553 50.258823,17.248793 50.2585445,17.248959 50.2583916,17.2493681 50.2580621,17.2497696 50.2576628,17.2500574 50.2574336,17.2503236 50.2571534,17.2508118 50.2565766,17.2510089 50.2564537,17.2510287 50.2564413,17.2511772 50.2564282,17.2515222 50.2565478,17.2517255 50.2566514,17.2518121 50.2566955,17.2519114 50.2568093,17.2516328 50.2570336,17.2513963 50.2572597,17.2512532 50.2574006,17.2511313 50.2575238,17.2510245 50.2576218,17.25099 50.2577588,17.250813 50.2579678,17.2506333 50.2581452,17.2504376 50.2582709,17.2503206 50.2583438,17.2502873 50.2584041,17.2502082 50.2584505,17.2501307 50.2585233,17.2500369 50.2586103,17.2495705 50.2590458,17.2488871 50.2597165,17.2488142 50.259788,17.2486068 50.259726,17.2484304 50.259628,17.2481759 50.259479,17.2481061 50.2592478),(17.2485434 50.2494851,17.2485585 50.2494392,17.2485607 50.2494324,17.2485597 50.2493203,17.2491759 50.2490444,17.2496028 50.2488267,17.2496653 50.2488958,17.2497612 50.2488956,17.2498539 50.2488337,17.2498105 50.2487867,17.2497447 50.2487382,17.2501064 50.2485232,17.2501556 50.2484807,17.2500806 50.2484215,17.2500511 50.2483982,17.2501078 50.2483625,17.2505959 50.2480554,17.2517878 50.2474557,17.2511976 50.2477369,17.2517135 50.2474627,17.2510309 50.2477669,17.2507311 50.2479285,17.2500609 50.2483336,17.2499943 50.2483738,17.2498753 50.2482867,17.2498199 50.2482534,17.2498327 50.2481926,17.2498359 50.2481776,17.2507001 50.2476745,17.2510866 50.2474895,17.2511095 50.2474198,17.2511107 50.2474161,17.2511253 50.2473222,17.2510763 50.2471893,17.2510033 50.246991,17.2509262 50.2468614,17.2509322 50.2467687,17.2509985 50.2466684,17.2510021 50.246663,17.2513253 50.2464867,17.2519523 50.2461951,17.2525191 50.2470732,17.2520144 50.247312,17.2519093 50.2473812,17.2520148 50.2473545,17.2525204 50.2471103,17.2526914 50.2473014,17.2527374 50.2473193,17.2528127 50.2473241,17.2529095 50.2473176,17.2529227 50.2473276,17.2530167 50.2473985,17.2533176 50.2476932,17.2533535 50.2478247,17.2533472 50.2478332,17.2532844 50.2479171,17.2532807 50.2479221,17.2527698 50.2481552,17.2526673 50.2481342,17.2524904 50.2481762,17.2522553 50.2483021,17.2521199 50.2482968,17.2521057 50.2482963,17.2518104 50.248318,17.2516933 50.2483738,17.2515891 50.2484096,17.2515692 50.2484472,17.2515742 50.2485247,17.2518861 50.2486609,17.2520658 50.2487292,17.252232 50.2487529,17.2524662 50.2488203,17.2525947 50.2488679,17.252693 50.2489353,17.2527192 50.248984,17.252687 50.2490794,17.2505994 50.2499581,17.2504116 50.2500789,17.2513396 50.2497009,17.252677 50.2491167,17.2526986 50.2495421,17.2521384 50.2499731,17.2505213 50.2506162,17.2504527 50.2506678,17.2521164 50.2500603,17.2521591 50.250261,17.2521073 50.250328,17.252 50.2504476,17.2519428 50.2504801,17.2519241 50.2505187,17.2519168 50.2505663,17.2518501 50.2506512,17.2517758 50.2507667,17.2516002 50.2509361,17.2516997 50.2509307,17.2518284 50.2508902,17.2518404 50.2508864,17.2518459 50.2508941,17.2519225 50.2510018,17.2519059 50.2511092,17.2518051 50.2512139,17.2517067 50.2513512,17.251643 50.251414,17.251477 50.2514576,17.2512969 50.2517379,17.2512101 50.2518607,17.2511362 50.2519653,17.2511112 50.2519998,17.2509566 50.2521788,17.2508112 50.2523348,17.2507878 50.2522403,17.2507296 50.2521977,17.2506748 50.252215,17.2505475 50.2522958,17.2505145 50.2522894,17.250489 50.2522971,17.2504789 50.2523002,17.2504589 50.2523178,17.2504175 50.2523543,17.2503024 50.2524824,17.2501947 50.2525547,17.2501342 50.252541,17.249878 50.2524831,17.2497891 50.2523934,17.2496705 50.2523135,17.2494699 50.2522709,17.2493569 50.2521824,17.2495274 50.2519937,17.2495594 50.2519582,17.2497703 50.2517246,17.2499389 50.2516585,17.2501408 50.2515793,17.2511294 50.2511554,17.2510382 50.2511442,17.250052 50.2515709,17.2498967 50.2515818,17.2496362 50.2513357,17.2495437 50.2511058,17.2496007 50.251071,17.2498892 50.2508948,17.2495607 50.251002,17.2494722 50.2510308,17.2492607 50.2506027,17.2492613 50.2505547,17.2493239 50.2505288,17.2495446 50.2504372,17.2498002 50.2502784,17.2495711 50.2503608,17.2494199 50.2501874,17.2493882 50.2501511,17.2492147 50.249979,17.2491094 50.2499133,17.2491024 50.2499116,17.2489158 50.2498679,17.2487084 50.2496694,17.2486662 50.2495782,17.2486752 50.2495406,17.2486822 50.2495115,17.2492135 50.2492861,17.2496018 50.24916,17.2499335 50.2490014,17.2502854 50.2487402,17.250849 50.248413,17.2516676 50.2479667,17.2522224 50.2476785,17.2524698 50.2475435,17.2514576 50.2479628,17.2512089 50.248136,17.2511597 50.2481537,17.2511063 50.2481981,17.2509733 50.2482926,17.2508791 50.2483643,17.2505259 50.2485359,17.2501269 50.2488358,17.2497581 50.249016,17.2493678 50.249166,17.2489478 50.2493316,17.2485906 50.2494672,17.2485434 50.2494851),(17.2489495 50.25992,17.2489679 50.259801,17.2489892 50.2597706,17.2491037 50.2596073,17.2494681 50.2592295,17.2501585 50.2585942,17.2506404 50.2581588,17.2508201 50.2579814,17.2509971 50.2577724,17.2511684 50.2575709,17.2514703 50.2572686,17.2517918 50.2573216,17.2519451 50.2573964,17.2520325 50.2574508,17.2521822 50.2574576,17.2522952 50.257556,17.2521631 50.2577407,17.2520095 50.2579306,17.2510832 50.2587985,17.25084 50.2590884,17.2505571 50.2593495,17.2504204 50.2594673,17.2502977 50.2595588,17.2501039 50.2597633,17.249901 50.2599142,17.2497232 50.2600837,17.2497148 50.2600917,17.2495567 50.2600391,17.249437 50.2599927,17.2490763 50.2599471,17.2489495 50.25992),(17.2498805 50.2602134,17.249895 50.2601926,17.2499802 50.2600707,17.2501284 50.25996,17.2504545 50.2596926,17.2506434 50.2596378,17.2506846 50.2595717,17.2506714 50.2594751,17.2506918 50.2594168,17.2507918 50.2593308,17.2511894 50.2590191,17.2518453 50.2583214,17.2525623 50.2577239,17.2531364 50.2572745,17.2543371 50.2562462,17.2550589 50.2556536,17.2552976 50.2555224,17.2554292 50.2554278,17.255617 50.2552709,17.2557555 50.2551135,17.2561151 50.2553388,17.2561857 50.2554471,17.2562003 50.2555249,17.2561814 50.2555671,17.2561423 50.255654,17.2560203 50.2558323,17.2557471 50.256095,17.2552608 50.2565336,17.2551803 50.2566062,17.2547 50.2569957,17.2540765 50.2574817,17.2538057 50.2576469,17.2536627 50.2576513,17.2535478 50.2576377,17.253366 50.2575746,17.2532738 50.2575877,17.2531758 50.2576013,17.2530802 50.2576278,17.2531272 50.2576786,17.2534504 50.2577842,17.2535113 50.2578459,17.2533101 50.2580625,17.2529342 50.2583687,17.251468 50.2597647,17.2505907 50.2605947,17.2504167 50.2607173,17.2502165 50.2608454,17.2501374 50.2608829,17.2500085 50.2608163,17.24996 50.2607912,17.2499207 50.2606929,17.2499135 50.2606274,17.2499549 50.2605695,17.2499598 50.2605487,17.2499838 50.2604467,17.249964 50.2602928,17.2499026 50.2602344,17.2498805 50.2602134),(17.2503794 50.2611847,17.2503944 50.2611061,17.2504093 50.2610194,17.2504912 50.2609181,17.2506109 50.2608462,17.2507738 50.2607048,17.2509875 50.2605257,17.25106 50.2604765,17.2512633 50.2602337,17.2518403 50.2596664,17.2529807 50.2585695,17.2537343 50.2579137,17.2539432 50.2577415,17.2545022 50.2573166,17.2550891 50.2568349,17.2553642 50.2566627,17.2554687 50.2566391,17.255767 50.2567679,17.2559422 50.2568889,17.2561021 50.256959,17.2561243 50.257006,17.2561313 50.2570208,17.256106 50.2570609,17.2560799 50.2571024,17.2557342 50.2573798,17.2551034 50.2578438,17.2546655 50.2581814,17.2540358 50.2578983,17.2538892 50.257935,17.2538765 50.2580173,17.2544961 50.2582835,17.2521807 50.2603241,17.2515641 50.2609467,17.2514796 50.2609912,17.2513704 50.2609943,17.2512424 50.2609813,17.2511376 50.2609484,17.2511327 50.2609489,17.2510603 50.2609562,17.2509701 50.2609558,17.2508495 50.2609888,17.2507316 50.26104,17.2505858 50.2611626,17.2505281 50.2612167,17.2504056 50.2612703,17.2503794 50.2611847),(17.2517661 50.2455968,17.2518167 50.2454858,17.2518204 50.2454777,17.2522534 50.2452572,17.2526893 50.2450353,17.2537125 50.2445905,17.2539185 50.244501,17.2540417 50.2444212,17.2547683 50.2439502,17.2549122 50.2439732,17.2551221 50.2440068,17.255246 50.2440266,17.2555007 50.2441537,17.2555453 50.2441759,17.2552086 50.2445756,17.2543589 50.2449733,17.2542832 50.2449991,17.2541732 50.2449385,17.2541259 50.2449355,17.2539166 50.2449757,17.2537901 50.2450213,17.2536624 50.2450744,17.253569 50.2451374,17.253134 50.2453241,17.2529107 50.2454219,17.252737 50.2454979,17.2520311 50.2456596,17.2518963 50.2456817,17.251888 50.245675,17.2517661 50.2455968),(17.2522109 50.2461086,17.252263 50.2460451,17.2523702 50.2459986,17.2530835 50.2458409,17.2535445 50.2456751,17.2544135 50.2453493,17.2549973 50.245046,17.2553071 50.2448832,17.2554752 50.244762,17.25569 50.2446303,17.2558959 50.2445106,17.2561274 50.2444712,17.2562959 50.2444657,17.2564803 50.2444937,17.2567417 50.244598,17.257083 50.2447317,17.2572647 50.2448138,17.257569 50.245068,17.2576736 50.245184,17.2578229 50.2452929,17.2578918 50.2453488,17.2579872 50.2454145,17.2581599 50.2455547,17.2582205 50.2455911,17.2582148 50.2456548,17.2581276 50.245727,17.2579155 50.2458047,17.2577635 50.2458538,17.2574424 50.2459789,17.2572304 50.2460618,17.2572225 50.2460948,17.2572801 50.2460867,17.257392 50.2460468,17.2575741 50.2459808,17.2578634 50.2459043,17.2580468 50.2458573,17.2582964 50.2457739,17.2584203 50.2458016,17.2585476 50.2458376,17.2586725 50.2459161,17.2587873 50.2460161,17.258803 50.2460479,17.2587711 50.2460768,17.2586903 50.2461113,17.2584412 50.2462587,17.2580657 50.2465171,17.2583188 50.2464293,17.2586759 50.2462344,17.2589168 50.2461612,17.2589729 50.246167,17.2590237 50.2461723,17.2591107 50.2462738,17.2593069 50.2464241,17.2593096 50.2464507,17.2593027 50.2464619,17.2592913 50.2464804,17.2591382 50.2466767,17.2590065 50.2468183,17.2589386 50.2468615,17.258786 50.2469586,17.2583258 50.2471851,17.2579674 50.2473298,17.2576219 50.2474357,17.257608 50.2474375,17.257482 50.2474533,17.2574345 50.2474503,17.2574121 50.247418,17.2573971 50.2473817,17.2573845 50.247022,17.2573923 50.2468807,17.2573125 50.2468051,17.2571985 50.2467952,17.2570267 50.2468131,17.2569725 50.246863,17.256887 50.2469126,17.2568884 50.2469479,17.2569339 50.2469641,17.2570748 50.2470023,17.2571808 50.247,17.2572617 50.2471054,17.257266 50.2471661,17.2572247 50.2473443,17.2571793 50.2475487,17.257128 50.2476579,17.2569882 50.2477637,17.2567459 50.2478673,17.2564289 50.2480103,17.2560529 50.2482246,17.2557856 50.248416,17.25615 50.2482686,17.2563984 50.2481138,17.2566846 50.2479476,17.2570299 50.2478126,17.2570547 50.2478773,17.2571021 50.2479896,17.2571445 50.248098,17.2571432 50.2482244,17.2570899 50.2483041,17.257063 50.2483443,17.2569391 50.2484447,17.256693 50.248564,17.256651 50.2485823,17.2566392 50.2486584,17.2568464 50.2487329,17.2571454 50.2488596,17.2572976 50.2490373,17.2572423 50.2491575,17.2572775 50.2492415,17.2572849 50.2492814,17.2573775 50.2493846,17.2574557 50.2494719,17.2575132 50.2496644,17.2576294 50.2498687,17.2576748 50.250167,17.2576957 50.250359,17.2576924 50.250553,17.2577708 50.2507748,17.2577777 50.2509081,17.257788 50.2511092,17.2577336 50.2512012,17.2577174 50.2512285,17.2576421 50.2512418,17.2575319 50.2511913,17.2570386 50.2510082,17.2568402 50.2509251,17.256681 50.2508797,17.2564527 50.2508706,17.2563617 50.2508033,17.2561747 50.2507643,17.2561592 50.2507692,17.256034 50.2508087,17.2559447 50.2507939,17.2558483 50.2507616,17.2558166 50.2507032,17.2557493 50.2505457,17.2557262 50.2504404,17.2556465 50.2502362,17.2555161 50.2500715,17.2553087 50.2499982,17.2551663 50.2498807,17.2549726 50.2497943,17.254865 50.2497522,17.2548625 50.2497051,17.2549262 50.2496847,17.2549669 50.2496279,17.2549992 50.249595,17.2549905 50.2495638,17.254944 50.2495565,17.2549189 50.2495569,17.2548349 50.2495583,17.2547395 50.2495938,17.254604 50.2496441,17.2545227 50.2495795,17.2543702 50.2494722,17.2542874 50.2493793,17.2542378 50.2492813,17.2542622 50.2492151,17.254274 50.2491878,17.254292 50.2491465,17.2548664 50.2489371,17.2551238 50.2487943,17.2554278 50.2485861,17.2554135 50.2485896,17.255201 50.2486334,17.2550909 50.2487042,17.2550239 50.2487588,17.2547639 50.2489319,17.2546647 50.2489634,17.2544524 50.249024,17.25441 50.2489978,17.2543642 50.2489389,17.2541927 50.2489451,17.254084 50.2488469,17.2543783 50.2488476,17.2544455 50.2488049,17.2543688 50.2486998,17.2543856 50.2485915,17.2544081 50.2484195,17.2548085 50.2482084,17.2550019 50.248115,17.2551743 50.2479841,17.2552496 50.2479355,17.2552333 50.247908,17.2551851 50.2479093,17.2550072 50.2480391,17.2549014 50.2481029,17.2546644 50.2481716,17.2541879 50.2484147,17.2538051 50.2485373,17.2535378 50.248635,17.2533363 50.2486899,17.2531232 50.248783,17.2529558 50.2487552,17.2529341 50.2487185,17.2529328 50.2487128,17.2528993 50.2485645,17.2529265 50.2483892,17.2530491 50.2482525,17.2531478 50.2482064,17.2533482 50.2481911,17.2533935 50.2481877,17.2534818 50.2481933,17.2536024 50.248182,17.2536875 50.2481965,17.2538242 50.2482052,17.2539679 50.2481978,17.2540541 50.2481724,17.2540867 50.2481392,17.2541016 50.2480872,17.2540955 50.2480383,17.2540805 50.2480021,17.2540194 50.2479541,17.2540211 50.2478899,17.2539627 50.2478211,17.2539327 50.2477785,17.2539165 50.2477007,17.2538943 50.247655,17.2538723 50.2475764,17.2536573 50.2473495,17.2534547 50.2471356,17.2533745 50.2470898,17.2533188 50.2470944,17.2532488 50.2471008,17.2531721 50.247141,17.2530915 50.2471612,17.2530232 50.247202,17.2529417 50.2472465,17.2528923 50.2472379,17.2528525 50.2472038,17.2528138 50.2471625,17.252507 50.2467608,17.2522583 50.2462481,17.2522273 50.2461819,17.2522212 50.2461689,17.2522109 50.2461086),(17.2522209 50.2568449,17.2522858 50.2567623,17.2526293 50.2564644,17.2532211 50.2560378,17.2538427 50.2555784,17.2540292 50.2554244,17.2542294 50.2551599,17.2544717 50.2549422,17.2545309 50.2548383,17.254646 50.2546363,17.2547178 50.2545821,17.2547833 50.2545682,17.254838 50.254605,17.2549013 50.2546525,17.2549855 50.2549271,17.2550704 50.255199,17.2550543 50.2554027,17.2550058 50.2554703,17.2548761 50.2556509,17.2545166 50.2560173,17.2538774 50.2564358,17.2537911 50.2564779,17.253699 50.2565633,17.2535074 50.256599,17.2533511 50.2566351,17.2531473 50.2566953,17.253077 50.2567771,17.2525989 50.2569043,17.2522572 50.2568924,17.2522209 50.2568449),(17.2532034 50.2453589,17.2533081 50.2453346,17.2534356 50.245305,17.2538742 50.2451721,17.2544193 50.2450461,17.2546732 50.2449286,17.2549688 50.2448131,17.2554616 50.2444845,17.255686 50.2442091,17.2557525 50.2441275,17.2560015 50.2442202,17.2559168 50.2442782,17.2555102 50.2445566,17.2548293 50.244942,17.253963 50.2452927,17.2534263 50.2455188,17.2533535 50.2455446,17.2532034 50.2453589),(17.260209 50.2510963,17.2602409 50.2510634,17.2602594 50.2510444,17.2603836 50.2509792,17.2605036 50.2509137,17.261321 50.250576,17.2616289 50.2504433,17.2621324 50.2502802,17.2622131 50.2502827,17.2623196 50.2504412,17.262366 50.2506239,17.2623324 50.250695,17.2621039 50.2508512,17.2615447 50.2511236,17.2608121 50.2514273,17.2606599 50.2514874,17.2606344 50.2514974,17.2605257 50.2514715,17.2604365 50.2514288,17.2603575 50.2513569,17.260225 50.2511841,17.260209 50.2510963),(17.2604969 50.245315,17.26069 50.245252,17.2611 50.245174,17.2609234 50.2447882,17.261083 50.24447,17.2611338 50.2444254,17.2615867 50.2445496,17.262461 50.2447509,17.262825 50.245494,17.2617624 50.2452105,17.2617385 50.245475,17.262351 50.245769,17.262667 50.245902,17.263146 50.245799,17.265612 50.24735,17.265483 50.247194,17.265786 50.247375,17.26609 50.247555,17.266175 50.247936,17.2661887 50.248091,17.266709 50.248512,17.2669305 50.2488615,17.2672553 50.2490716,17.2674279 50.249245,17.2675557 50.2493846,17.267391 50.249746,17.264797 50.250149,17.264725 50.250149,17.2644163 50.2498426,17.2641776 50.2496514,17.2638304 50.2492827,17.2637255 50.2491567,17.2635128 50.2489455,17.2623935 50.2492729,17.2617755 50.2494745,17.2617082 50.2494028,17.2616757 50.2493957,17.2615375 50.2493146,17.2613665 50.2491176,17.2612591 50.2489834,17.2612956 50.2489634,17.2612886 50.248956,17.2625948 50.2482627,17.2636659 50.2479264,17.26377 50.2478895,17.2638986 50.2478534,17.2642986 50.2477278,17.263022 50.2469539,17.26189 50.247724,17.261506 50.246983,17.2616927 50.2467907,17.2620128 50.2465703,17.2624396 50.2460473,17.262354 50.2459739,17.2616479 50.2457242,17.2610714 50.2460551,17.2604969 50.245315),(17.2827088 50.2588659,17.2827332 50.2587627,17.2828371 50.2585371,17.2829222 50.2583239,17.2829878 50.2583001,17.2830272 50.2582005,17.2831441 50.2581891,17.2832289 50.2581808,17.28339 50.2581414,17.2834686 50.2580795,17.2835893 50.257903,17.2837058 50.2577009,17.2838939 50.2575382,17.283956 50.2574374,17.2839996 50.2573054,17.2839094 50.257187,17.2838544 50.2570868,17.2838599 50.2569969,17.2839474 50.2568769,17.2840899 50.2569582,17.284067 50.2567688,17.2840263 50.2566692,17.284023 50.2566612,17.284103 50.256537,17.2842019 50.256379,17.2842195 50.2563741,17.2843947 50.2563253,17.284675 50.2562988,17.2850163 50.2563151,17.284916 50.2564955,17.2843102 50.2574544,17.284176 50.2576205,17.2840747 50.2577239,17.2839563 50.2580328,17.2838164 50.2583635,17.283734 50.2585507,17.2836575 50.2586994,17.2836055 50.2588623,17.2835158 50.2589496,17.2835044 50.2589607,17.2833743 50.2589633,17.2832574 50.258945,17.2829532 50.2588986,17.2827088 50.2588659),(17.2828006 50.2648021,17.2828559 50.2645265,17.2829394 50.2643511,17.2829605 50.264309,17.2829863 50.2642574,17.2830078 50.264191,17.2830036 50.2640815,17.283037 50.263865,17.283071 50.2637,17.2831043 50.2635937,17.2831358 50.2634991,17.2831805 50.2634107,17.2832033 50.2632992,17.2833394 50.2632121,17.2835486 50.2632353,17.2836438 50.2632757,17.2837323 50.2633168,17.2837319 50.2633987,17.2836955 50.2638354,17.2836819 50.2640053,17.2835963 50.2643133,17.2835641 50.2644666,17.2834487 50.2648035,17.2833454 50.264913,17.2832772 50.2649436,17.2831383 50.2649639,17.2829217 50.264967,17.282892 50.2649509,17.2828216 50.2649127,17.2828006 50.2648021),(17.2830043 50.2656732,17.2830222 50.2655207,17.2831324 50.2654645,17.2831665 50.2654385,17.2832348 50.2653864,17.2833096 50.2653294,17.2833603 50.2652367,17.2834943 50.2649916,17.2835713 50.2647835,17.2836443 50.2645864,17.2838804 50.2646909,17.2838928 50.2647545,17.2839253 50.2649204,17.2838223 50.2651712,17.2837558 50.2653333,17.2836288 50.2655258,17.2835573 50.265576,17.2835213 50.2656012,17.283452 50.2656944,17.2832792 50.2657819,17.2831761 50.2657877,17.2831601 50.2657886,17.2831058 50.2657916,17.2830337 50.2657574,17.2830244 50.265753,17.2830043 50.2656732),(17.2832873 50.2609726,17.2833042 50.2609425,17.2834174 50.2607413,17.2834424 50.2606253,17.2834631 50.2604911,17.2834741 50.2603743,17.2835046 50.2602225,17.2835693 50.2601227,17.2838898 50.2598266,17.2839448 50.2596991,17.284085 50.2593956,17.2842783 50.2591651,17.2843109 50.2591132,17.2843403 50.2590357,17.2843695 50.258824,17.2841439 50.2585376,17.2841021 50.2584675,17.2840948 50.2584243,17.2842061 50.2581571,17.2842918 50.2579193,17.2844298 50.2577751,17.2844581 50.257705,17.2844813 50.2576233,17.2845162 50.2575558,17.284548 50.2574634,17.2847458 50.2571128,17.2852092 50.2564947,17.2852642 50.2564257,17.2858026 50.255663,17.2863141 50.2551873,17.2864951 50.2551044,17.2867761 50.2550548,17.286833 50.2550494,17.2868913 50.2550576,17.286923 50.2550798,17.2869192 50.2551268,17.2868241 50.2553568,17.2866923 50.2557341,17.2865571 50.25602,17.2863023 50.2563083,17.2860966 50.256574,17.285778 50.2570709,17.2857221 50.2572366,17.2853891 50.257827,17.2851206 50.2581814,17.2849478 50.2584605,17.2846456 50.2591236,17.2845486 50.2593441,17.2843086 50.2599888,17.2841706 50.2605631,17.2839129 50.2613648,17.2837731 50.2616316,17.2836943 50.2616854,17.2835709 50.2616265,17.2835631 50.2616228,17.2835506 50.2615993,17.2834483 50.2614076,17.2833072 50.2612269,17.2832899 50.2610062,17.2832873 50.2609726),(17.2842962 50.2606397,17.2843126 50.2603968,17.2844921 50.2598644,17.2847343 50.2592176,17.2849511 50.2587716,17.285175 50.2583767,17.2858971 50.2572584,17.2862782 50.256565,17.2866807 50.2560386,17.2868649 50.2557632,17.2869531 50.2555942,17.2870206 50.2555586,17.2871368 50.2555482,17.2876166 50.2556807,17.2877237 50.2557279,17.2877268 50.2558079,17.2874915 50.2562769,17.287296 50.2564887,17.2871303 50.2566579,17.287052 50.2568092,17.2870156 50.2569632,17.2870109 50.2570758,17.2868897 50.2572678,17.286693 50.25751,17.2865093 50.2577143,17.2863133 50.2580713,17.2858566 50.2588793,17.2858298 50.2589525,17.2858483 50.2589836,17.2858852 50.2589959,17.2859274 50.2589736,17.2860225 50.2588599,17.2862004 50.2585619,17.2863085 50.2583143,17.2865125 50.257998,17.2866536 50.2577375,17.2868753 50.257452,17.2873751 50.2567779,17.2875521 50.2567281,17.2877985 50.2568205,17.2875034 50.2573537,17.2874351 50.2574857,17.2875607 50.2576581,17.2876916 50.2577134,17.2875731 50.2579976,17.2874602 50.2581721,17.2873556 50.2583202,17.2872666 50.2584942,17.2872425 50.2585963,17.287059 50.258918,17.2870518 50.259138,17.28702 50.2593437,17.2868999 50.2596839,17.2868344 50.2600347,17.2869548 50.2600857,17.2870187 50.2602831,17.2873103 50.2604208,17.2873528 50.2605012,17.2873506 50.2607161,17.2873227 50.2608516,17.2872896 50.2610293,17.2872628 50.2612028,17.2866305 50.2625629,17.2866067 50.2625664,17.2865776 50.2626044,17.2863998 50.2629953,17.2863149 50.2631986,17.2859694 50.2637747,17.2858682 50.2637307,17.2857215 50.2637264,17.2855809 50.2637823,17.2853105 50.2637799,17.2852059 50.2636986,17.2851782 50.263627,17.2851927 50.2635332,17.2853461 50.2633433,17.2853974 50.263162,17.2855222 50.2627558,17.2854067 50.2628835,17.2853363 50.2629839,17.2851847 50.263135,17.2851472 50.2633684,17.2850359 50.2634434,17.2849719 50.2635181,17.284804 50.2635384,17.2847379 50.2635143,17.2847224 50.2634634,17.2847576 50.2633359,17.2847207 50.2632737,17.2847053 50.2632228,17.2847144 50.2631636,17.2847804 50.2630879,17.2848902 50.26303,17.2849064 50.2629566,17.2848488 50.2629376,17.2847701 50.2629362,17.2847272 50.2628946,17.2847202 50.2627748,17.2847953 50.26259,17.2848151 50.2624615,17.2847162 50.2622995,17.2847682 50.2620905,17.2849151 50.2618424,17.2849859 50.2616573,17.2849228 50.2615635,17.2849173 50.2614983,17.2849365 50.2614247,17.284928 50.2613792,17.2848742 50.2613758,17.2848189 50.2613823,17.2847075 50.2614002,17.2846061 50.2614037,17.28449 50.2613514,17.2843778 50.2612745,17.2843339 50.2612068,17.2843239 50.2611214,17.2843307 50.261027,17.2843781 50.260812,17.2842962 50.2606397),(17.2854921 50.2640561,17.2856318 50.2639899,17.2857902 50.2639053,17.2858238 50.2638874,17.2859369 50.2638395,17.2859915 50.263796,17.2860361 50.2637356,17.2863893 50.2631636,17.2864382 50.2630546,17.2866552 50.2626044,17.286652 50.2625742,17.2866466 50.2625458,17.2872816 50.2611959,17.2873848 50.2610425,17.2875026 50.2608359,17.2876068 50.2605264,17.2876892 50.260294,17.2877754 50.2602281,17.2878978 50.2603118,17.2879209 50.2604361,17.2879166 50.2606553,17.2879526 50.260906,17.2879506 50.2611031,17.2879579 50.2611819,17.2879756 50.2612408,17.2879703 50.261348,17.2880032 50.2615,17.287987 50.261751,17.2880508 50.2619131,17.2879779 50.2620747,17.28792 50.2622007,17.2879228 50.2622195,17.2879477 50.262389,17.2880841 50.2624916,17.2880764 50.2625947,17.2878824 50.2629466,17.2876919 50.2632476,17.2874673 50.2636023,17.2873427 50.2637245,17.2872468 50.2637799,17.2871229 50.2638063,17.2869668 50.2638015,17.2867162 50.2638483,17.2865342 50.2638683,17.2862082 50.2640265,17.2860638 50.2640851,17.2858532 50.2641169,17.285675 50.2641275,17.2856676 50.2641278,17.2855736 50.2641311,17.2855237 50.264103,17.2854921 50.2640561),(17.2972134 50.2879153,17.2972345 50.2878555,17.2973025 50.2878149,17.2973615 50.2878201,17.2973979 50.2878379,17.2974514 50.2878936,17.2975068 50.2879074,17.2975539 50.2879001,17.2975844 50.2878814,17.2975934 50.2878503,17.2975377 50.2877907,17.2974498 50.2877257,17.2974817 50.2876878,17.2978523 50.2876526,17.2980163 50.2876464,17.2980671 50.2876304,17.2981383 50.2875568,17.2982786 50.2874845,17.2983139 50.2874471,17.2983146 50.287428,17.2982929 50.2874045,17.2981922 50.2873863,17.2980598 50.2873947,17.2978662 50.287462,17.2976651 50.2875134,17.2976268 50.2875171,17.2975856 50.2875159,17.2975354 50.287498,17.2975265 50.2874902,17.2975122 50.2874708,17.2975036 50.2874208,17.2975299 50.2873756,17.2977805 50.2871549,17.297817 50.2871228,17.2980972 50.2867611,17.298193 50.2866333,17.2982442 50.2865654,17.2982448 50.2864639,17.2982069 50.2863519,17.2980555 50.2860837,17.298052 50.2859601,17.2980845 50.2858842,17.2981129 50.2858512,17.2981673 50.2858114,17.298198 50.2857635,17.2981594 50.2856612,17.2981562 50.2855313,17.2982657 50.2852239,17.2983264 50.2851829,17.2983949 50.2851625,17.2984209 50.2851548,17.2984293 50.2851533,17.2986399 50.2851909,17.2989821 50.2852635,17.2993967 50.2854016,17.2994973 50.2854291,17.29955 50.2854289,17.2996 50.2854238,17.2996438 50.2854101,17.2998771 50.2852561,17.2999631 50.2852001,17.3001639 50.2850692,17.3003606 50.2849272,17.3005982 50.2846848,17.3007605 50.284448,17.3008621 50.2842282,17.300877 50.284196,17.3014615 50.2833749,17.3016858 50.2831607,17.3017163 50.2831316,17.3018492 50.2830751,17.3019737 50.283073,17.3021259 50.2830927,17.3022205 50.2831336,17.3022682 50.2831765,17.3022341 50.2836819,17.3021604 50.2841275,17.3020568 50.2844382,17.301629 50.2851581,17.301327 50.2857576,17.3010852 50.2865704,17.3010774 50.2868252,17.3011394 50.2872094,17.3012044 50.2879417,17.3011994 50.2880035,17.3011514 50.2880635,17.3010715 50.2880949,17.3009783 50.2881008,17.3009408 50.2880963,17.3007967 50.2880659,17.3007688 50.2880661,17.3007369 50.2880763,17.3007196 50.2880956,17.3006368 50.2882249,17.3005286 50.2883458,17.3004366 50.2884366,17.3003743 50.2884633,17.3003444 50.288473,17.3003144 50.288491,17.3002445 50.2885881,17.3001875 50.2886459,17.3001118 50.2887098,17.3001008 50.288719,17.3000423 50.2887273,17.3000086 50.2887277,17.2999784 50.2887245,17.2999474 50.2887139,17.2999166 50.2886974,17.2998965 50.288675,17.2998923 50.2886522,17.299901 50.2885822,17.299877 50.2885586,17.2998407 50.2885379,17.2997927 50.2885385,17.2996625 50.2885856,17.2996208 50.2885939,17.2995681 50.288585,17.2995306 50.2885676,17.2995237 50.2885377,17.2995422 50.2884622,17.2996554 50.2882112,17.2996683 50.2881518,17.299663 50.288097,17.299639 50.2880586,17.2995854 50.2880342,17.2995449 50.2880316,17.2994856 50.2880505,17.2994447 50.2880802,17.2994197 50.2881228,17.2993921 50.2882667,17.2993779 50.2883017,17.2993651 50.2883118,17.29933 50.2883212,17.2992857 50.2883252,17.2992355 50.2883237,17.2992001 50.288319,17.2991633 50.2883059,17.299058 50.2882429,17.2990568 50.2882395,17.2989375 50.2882053,17.2988265 50.2881627,17.2987196 50.2880938,17.2986483 50.2880015,17.2986216 50.2879567,17.2986021 50.287907,17.2985764 50.2878888,17.2985483 50.2878871,17.2985209 50.2878969,17.2984856 50.2879829,17.2984698 50.2880018,17.2984437 50.28802,17.2983982 50.2880246,17.2983266 50.2880139,17.2983167 50.2880112,17.298315 50.288011,17.2982397 50.287973,17.2981269 50.2879437,17.298002 50.2879181,17.2978218 50.2879082,17.2977918 50.287924,17.2978009 50.2879393,17.297943 50.2880151,17.2980419 50.2880621,17.2981306 50.2881134,17.2981781 50.2881489,17.2981978 50.2881911,17.2981648 50.288235,17.2981174 50.2882556,17.2980168 50.2882799,17.2979812 50.2882885,17.2978822 50.2882923,17.297781 50.2882795,17.2976049 50.2882261,17.297469 50.2881674,17.2974447 50.2881561,17.2973034 50.2880758,17.2972462 50.2880309,17.2972247 50.2879832,17.2972134 50.2879153),(17.2996876 50.2437912,17.2997093 50.2437407,17.2997378 50.2437117,17.2998007 50.2436926,17.299873 50.2436908,17.2999655 50.243707,17.3000067 50.2437476,17.2999938 50.2437924,17.29992 50.2438486,17.2998433 50.2438716,17.2997648 50.2438679,17.2996998 50.2438283,17.2996876 50.2437912),(17.2998227 50.2890216,17.2999515 50.2887783,17.3001419 50.2887492,17.3003377 50.2885212,17.3005254 50.2884133,17.3007803 50.2881099,17.3011477 50.2881442,17.3012121 50.2883738,17.3011209 50.2886686,17.3009787 50.2890302,17.3009626 50.2891879,17.3006917 50.2892221,17.3004396 50.2891622,17.2998227 50.2890216),(17.304001 50.244578,17.305517 50.24359,17.306308 50.243713,17.30715 50.244988,17.307673 50.245071,17.310275 50.24582,17.31121 50.246472,17.3116767 50.2473202,17.3114323 50.2478966,17.311015 50.247693,17.308275 50.246214,17.307112 50.246103,17.304001 50.244578),(17.3106149 50.2488179,17.3106287 50.2487022,17.310667 50.2486687,17.3106877 50.2486624,17.310711 50.2486554,17.3108486 50.2486477,17.3109813 50.2486517,17.3110913 50.2486757,17.311169 50.2487098,17.3112531 50.248767,17.3112811 50.2488296,17.3112782 50.2488611,17.3112459 50.2488961,17.3112141 50.2489306,17.3111553 50.2489661,17.3110493 50.2490127,17.3109227 50.2490008,17.3106815 50.2489414,17.31063 50.2489125,17.3106149 50.2488179),(17.3119019 50.2458858,17.3119617 50.2458313,17.3121079 50.2457544,17.3122055 50.2457238,17.3122946 50.2457122,17.312316 50.2457199,17.3123535 50.2457763,17.3123571 50.245869,17.3123266 50.2459387,17.3122736 50.2459841,17.3122285 50.2460043,17.3121552 50.2460001,17.3120473 50.2459939,17.3119696 50.2459725,17.3119404 50.2459567,17.3119086 50.2459192,17.3119019 50.2458858),(17.3188702 50.2523128,17.3188944 50.2522983,17.3189809 50.2522995,17.3191515 50.2523471,17.3192585 50.2523969,17.3194308 50.2525231,17.319645 50.2526469,17.319724 50.2527114,17.3198144 50.2528136,17.3198336 50.2528578,17.3198031 50.2528864,17.3196832 50.2528897,17.3196485 50.2528907,17.319462 50.252847,17.31932 50.2527936,17.3191153 50.2526856,17.3189927 50.2525829,17.3189334 50.2525056,17.318882 50.2523487,17.3188702 50.2523128),(17.3283438 50.2557401,17.3283712 50.2556841,17.3284308 50.2556374,17.3286209 50.2556663,17.3287914 50.2557275,17.3289084 50.2557973,17.3288039 50.2558436,17.3286533 50.2558726,17.3285731 50.2558819,17.3284866 50.2558596,17.3284168 50.2558264,17.3283636 50.2557822,17.3283438 50.2557401),(17.330488 50.2585394,17.3305064 50.2585117,17.33054 50.2584949,17.3308346 50.2582551,17.3308984 50.2582067,17.3309691 50.2582049,17.3310474 50.2582179,17.331203 50.2582874,17.3315213 50.2584258,17.3316876 50.2584715,17.3318137 50.2584948,17.3320806 50.2585916,17.3324289 50.2587249,17.3326906 50.258822,17.3327664 50.2588602,17.3327897 50.2589014,17.3327778 50.2589332,17.3327631 50.2589738,17.3327006 50.2590231,17.3325922 50.2591139,17.3325298 50.2591813,17.3324611 50.2592429,17.3323819 50.2593093,17.3322846 50.2593925,17.332137 50.2595278,17.332088 50.2595716,17.332046 50.259616,17.3320032 50.2596196,17.3319822 50.2596002,17.331978 50.2595358,17.3319348 50.259487,17.3318781 50.2594428,17.331813 50.2593899,17.3317518 50.2593481,17.3316641 50.2592766,17.3314595 50.2591589,17.3313486 50.2590833,17.3312948 50.2590393,17.3312305 50.258962,17.3311664 50.2589162,17.3308273 50.2587433,17.3305891 50.2586244,17.3305147 50.2585863,17.330497 50.2585635,17.330488 50.2585394))"
            </Parameter>
        </Datasource>
    </Layer>

    <Style name="lines">
        <Rule>
            <LineSymbolizer
                stroke="red"
                stroke-width="1"
                />

            <MarkersSymbolizer
                placement="interior"
                ignore-placement="true"
                allow-overlap="true"
                fill="blue"
                width="15"
                height="15"
                multi-policy="largest"
                />
            <MarkersSymbolizer
                placement="point"
                ignore-placement="true"
                allow-overlap="true"
                fill="green"
                width="15"
                height="15"
                multi-policy="largest"
                />

            <TextSymbolizer
                placement="interior"
                placement-type="simple"
                placements="N,S,W,E,NE,SE,NW,SW"
                face-name="DejaVu Sans Book"
                size="12"
                fill="blue"
                halo-radius="1"
                halo-fill="white"
                dx="12"
                dy="12"
                >
                "Interior"
            </TextSymbolizer>
            <TextSymbolizer
                placement="centroid"
                placement-type="simple"
                placements="N,S,W,E,NE,SE,NW,SW"
                face-name="DejaVu Sans Book"
                size="12"
                fill="green"
                halo-radius="1"
                halo-fill="white"
                dx="12"
                dy="12"
                >
                "Centroid"
            </TextSymbolizer>
        </Rule>
    </Style>
</Map>
